Workbook

Sheet Painel
B2: Painel do funil - Fase 1
B3: Tudo aqui se calcula a partir da aba Lista 200. Nao digite nada nesta aba.
B5: BOXES NA LISTA | D5: PRIORIDADE A | F5: JA ABORDADOS | H5: GANHOS | J5: VAGAS RESTANTES
B6: =COUNTA('Lista 200'!$B$2:$B$201) | D6: =COUNTIF('Lista 200'!$M$2:$M$201,"A") | F6: =SUM(C12:C18) | H6: =COUNTIF('Lista 200'!$N$2:$N$201,"Ganho") | J6: =20-COUNTIF('Lista 200'!$N$2:$N$201,"Ganho")
B9: Funil | F9: Taxas que importam
B10: Etapa | C10: Qtd | D10: % da lista | F10: Etapa | H10: Taxa
B11: Nao contatado | C11: =COUNTIF('Lista 200'!$N$2:$N$201,"Nao contatado") | D11: =IFERROR(C11/$B$6,0) | F11: Abordagem -> conversa | H11: =IFERROR((C13+C14+C15+C16+C17)/(C12+C13+C14+C15+C16+C17),0)
B12: Abordado | C12: =COUNTIF('Lista 200'!$N$2:$N$201,"Abordado") | D12: =IFERROR(C12/$B$6,0) | F12: Conversa -> demo feita | H12: =IFERROR((C15+C16+C17)/(C13+C14+C15+C16+C17),0)
B13: Conversando | C13: =COUNTIF('Lista 200'!$N$2:$N$201,"Conversando") | D13: =IFERROR(C13/$B$6,0) | F13: Demo feita -> ganho | H13: =IFERROR(C17/(C15+C16+C17),0)
B14: Demo agendada | C14: =COUNTIF('Lista 200'!$N$2:$N$201,"Demo agendada") | D14: =IFERROR(C14/$B$6,0) | F14: Ganho sobre lista trabalhada | H14: =IFERROR(C17/SUM(C12:C18),0)
B15: Demo feita | C15: =COUNTIF('Lista 200'!$N$2:$N$201,"Demo feita") | D15: =IFERROR(C15/$B$6,0)
B16: Proposta enviada | C16: =COUNTIF('Lista 200'!$N$2:$N$201,"Proposta enviada") | D16: =IFERROR(C16/$B$6,0)
B17: Ganho | C17: =COUNTIF('Lista 200'!$N$2:$N$201,"Ganho") | D17: =IFERROR(C17/$B$6,0) | F17: Ritmo
B18: Perdido | C18: =COUNTIF('Lista 200'!$N$2:$N$201,"Perdido") | D18: =IFERROR(C18/$B$6,0) | F18: Acoes vencidas (data passou e nao fechou) | H18: =SUMPRODUCT(('Lista 200'!$R$2:$R$201<>"")*('Lista 200'!$R$2:$R$201<TODAY())*('Lista 200'!$N$2:$N$201<>"Ganho")*('Lista 200'!$N$2:$N$201<>"Perdido")*('Lista 200'!$N$2:$N$201<>"Descartado"))
B19: Descartado | C19: =COUNTIF('Lista 200'!$N$2:$N$201,"Descartado") | D19: =IFERROR(C19/$B$6,0) | F19: Total de toques registrados | H19: =SUM('Lista 200'!$P$2:$P$201)
B22: Leitura: se Abordagem -> conversa ficar abaixo de ~20%, o problema esta na mensagem de abertura. Se Demo feita -> ganho ficar abaixo de ~30%, o problema esta na oferta ou na qualificacao - nao no volume de abordagens.

Sheet Metodo
B2: Metodo - como preencher e usar a Lista dos 200
B3: Fase 1 do plano de escala | meta: 20 boxes fundadores | ritmo alvo: 10 abordagens por dia
B5: 1. De onde tirar os 200 nomes
B6: Google Maps: buscar crossfit, cross training, box e treino funcional bairro por bairro. Instagram: as mesmas palavras + cidade, e os seguidores dos boxes que voce ja conhece.
B8: 2. O que preencher primeiro
B9: So as colunas amarelas. Score e Prioridade se calculam sozinhos. Nao pare para pesquisar tudo de um box: preencha o que da em 2 minutos e siga - a lista vale pelo volume, nao pela perfeicao de cada linha.
B11: 3. Como ler os sinais de dor
B12: WOD em foto de quadro branco no feed = nao tem sistema de treino. Sem app do aluno = a rotina do aluno vive no WhatsApp. Chama no direct pra saber valores = comercial e cobranca na mao do dono.
B14: 4. Por onde comecar a abordar
B15: So prioridade A. Nao gaste os primeiros dias com B e C: voce ainda esta aprendendo o script, e esse aprendizado fica caro se for gasto no lead errado.
B17: 5. O que fazer todo dia
B18: 10 abordagens novas, responder quem respondeu e mover o status de quem avancou. O Painel conta sozinho.
... B27: Tamanho do box (alunos)
B28: Entre 80 e 250 alunos (alvo) | C28: 30
B29: Entre 40 e 79, ou entre 251 e 400 | C29: 15
B30: Fora da faixa ou em branco | C30: 5
B31: Sistema que usa hoje
B32: Planilha ou caderno | C32: 25
B33: Nenhum sistema | C33: 25
B34: Desconhecido | C34: 10
B35: Concorrente | C35: 5
B36: Sinais de dor
B37: Peso por sinal marcado (ate 3) | C37: 10
B38: Regiao
B39: Grande SP | C39: 15
B40: SP interior | C40: 8
B41: Outro estado | C41: 3
B42: Corte de prioridade
B43: Score minimo para prioridade A | C43: 70
B44: Score minimo para prioridade B | C44: 50
B46: Amarelo = voce edita. Azul claro na Lista 200 = calculado, nao digite por cima.

Sheet Lista 200
A1: # | B1: Box | C1: Cidade / bairro | D1: Instagram | E1: WhatsApp | F1: Alunos (est.) | G1: Sistema hoje | H1: WOD no quadro | I1: Sem app aluno | J1: Cobranca manual | K1: Regiao | L1: Score | M1: Prior. | N1: Status | O1: Ultimo toque | P1: Toques | Q1: Proxima acao | R1: Quando | S1: Objecao principal | T1: Notas
A2: =IF($B2="","",ROW()-1) | B2: Endorfina Cross | C2: Guarulhos - SP | D2: @endorfinacross | E2: (11) 9xxxx-xxxx | F2: 180 | G2: Planilha ou caderno | H2: Sim | I2: Sim | J2: Sim | K2: Grande SP | L2: =IF($B2="","",IF($F2="",Metodo!$C$30,IF(AND($F2>=80,$F2<=250),Metodo!$C$28,IF(OR(AND($F2>=40,$F2<=79),AND($F2>=251,$F2<=400)),Metodo!$C$29,Metodo!$C$30)))+IFERROR(INDEX(Metodo!$C$32:$C$35,MATCH($G2,Metodo!$B$32:$B$35,0)),0)+COUNTIF($H2:$J2,"Sim")*Metodo!$C$37+IFERROR(INDEX(Metodo!$C$39:$C$41,MATCH($K2,Metodo!$B$39:$B$41,0)),0)) | M2: =IF($L2="","",IF($L2>=Metodo!$C$43,"A",IF($L2>=Metodo!$C$44,"B","C"))) | N2: Ganho | P2: 6 | Q2: Acompanhar uso semanal | S2: - | T2: Linha real e ja ganha: primeiro box em producao desde 23/05. Serve de modelo de preenchimento - comece a sua lista na linha 3.
A3: =IF($B3="","",ROW()-1) | B3: Arujá Crossfit Guarulhos | C3: Guarulhos - Centro | E3: +55 11 96646-4324 | K3: Grande SP | L3: =IF($B3="","",IF($F3="",Metodo!$C$30,IF(AND($F3>=80,$F3<=250),Metodo!$C$28,IF(OR(AND($F3>=40,$F3<=79),AND($F3>=251,$F3<=400)),Metodo!$C$29,Metodo!$C$30)))+IFERROR(INDEX(Metodo!$C$32:$C$35,MATCH($G3,Metodo!$B$32:$B$35,0)),0)+COUNTIF($H3:$J3,"Sim")*Metodo!$C$37+IFERROR(INDEX(Metodo!$C$39:$C$41,MATCH($K3,Metodo!$B$39:$B$41,0)),0)) | M3: =IF($L3="","",IF($L3>=Metodo!$C$43,"A",IF($L3>=Metodo!$C$44,"B","C"))) | N3: Nao contatado | Q3: Primeiro contato | T3: Tier 1 (varredura TomTom 2026-08-29, PR #185). Qualificacao: sem site. Sem Instagram proprio localizavel via busca - so aparece em agregador (FitFit.Fitness, nota 9,2/10 e 4,4/5). Endereco: Av. Paulo Faccini 691. Abertura generica (sem sinal especifico).
A4: =IF($B4="","",ROW()-1) | B4: CrossFit Forvy | C4: Guarulhos - Centro | D4: @crossfitforvy | E4: +55 11 93394-9736 | K4: Grande SP | L4: =IF($B4="","",IF($F4="",Metodo!$C$30,IF(AND($F4>=80,$F4<=250),Metodo!$C$28,IF(OR(AND($F4>=40,$F4<=79),AND($F4>=251,$F4<=400)),Metodo!$C$29,Metodo!$C$30)))+IFERROR(INDEX(Metodo!$C$32:$C$35,MATCH($G4,Metodo!$B$32:$B$35,0)),0)+COUNTIF($H4:$J4,"Sim")*Metodo!$C$37+IFERROR(INDEX(Metodo!$C$39:$C$41,MATCH($K4,Metodo!$B$39:$B$41,0)),0)) | M4: =IF($L4="","",IF($L4>=Metodo!$C$43,"A",IF($L4>=Metodo!$C$44,"B","C"))) | N4: Nao contatado | Q4: Primeiro contato | T4: Tier 1 (varredura TomTom 2026-08-29, PR #185). Qualificacao: afiliado oficial. Instagram @crossfitforvy, 3 mil seguidores, 511 posts, ativo. Fez Festivus Games em 2026-04.
A5: =IF($B5="","",ROW()-1) | B5: CrossFit MK-1 | C5: Guarulhos - Picanço | D5: @crossfitmk1 | E5: +55 11 98964-7226 | K5: Grande SP | L5: =IF($B5="","",IF($F5="",Metodo!$C$30,IF(AND($F5>=80,$F5<=250),Metodo!$C$28,IF(OR(AND($F5>=40,$F5<=79),AND($F5>=251,$F5<=400)),Metodo!$C$29,Metodo!$C$30)))+IFERROR(INDEX(Metodo!$C$32:$C$35,MATCH($G5,Metodo!$B$32:$B$35,0)),0)+COUNTIF($H5:$J5,"Sim")*Metodo!$C$37+IFERROR(INDEX(Metodo!$C$39:$C$41,MATCH($K5,Metodo!$B$39:$B$41,0)),0)) | M5: =IF($L5="","",IF($L5>=Metodo!$C$43,"A",IF($L5>=Metodo!$C$44,"B","C"))) | N5: Nao contatado | Q5: Primeiro contato | T5: Tier 1 (varredura TomTom 2026-08-29, PR #185). Qualificacao: site proprio. Instagram @crossfitmk1, 11,1 mil seguidores, desde 2012, pioneira em Guarulhos, tem CrossFit Kids. Possivel rede de 2 unidades com a MK1 Vila Galvao (linha 6) - confirmar.
A6: =IF($B6="","",ROW()-1) | B6: CrossFit MK1 Vila Galvão | C6: Guarulhos - Vila Galvão | D6: @crossfitmk1 | E6: +55 11 91223-9182 | K6: Grande SP | L6: =IF($B6="","",IF($F6="",Metodo!$C$30,IF(AND($F6>=80,$F6<=250),Metodo!$C$28,IF(OR(AND($F6>=40,$F6<=79),AND($F6>=251,$F6<=400)),Metodo!$C$29,Metodo!$C$30)))+IFERROR(INDEX(Metodo!$C$32:$C$35,MATCH($G6,Metodo!$B$32:$B$35,0)),0)+COUNTIF($H6:$J6,"Sim")*Metodo!$C$37+IFERROR(INDEX(Metodo!$C$39:$C$41,MATCH($K6,Metodo!$B$39:$B$41,0)),0)) | M6: =IF($L6="","",IF($L6>=Metodo!$C$43,"A",IF($L6>=Metodo!$C$44,"B","C"))) | N6: Nao contatado | Q6: Primeiro contato | T6: Tier 1 (varredura TomTom 2026-08-29, PR #185). Qualificacao: afiliado oficial. Mesma marca/Instagram da MK-1 Picanco (linha 5) - possivel 2a unidade da mesma rede, nao a mesma pessoa necessariamente. Confirmar antes de abordar como lead separado.
A7: =IF($B7="","",ROW()-1) | B7: CrossFit Saurus Bosque Maia | C7: Guarulhos - Vila Rio | D7: @crossfitsaurus | E7: +55 11 98254-0787 | K7: Grande SP | L7: =IF($B7="","",IF($F7="",Metodo!$C$30,IF(AND($F7>=80,$F7<=250),Metodo!$C$28,IF(OR(AND($F7>=40,$F7<=79),AND($F7>=251,$F7<=400)),Metodo!$C$29,Metodo!$C$30)))+IFERROR(INDEX(Metodo!$C$32:$C$35,MATCH($G7,Metodo!$B$32:$B$35,0)),0)+COUNTIF($H7:$J7,"Sim")*Metodo!$C$37+IFERROR(INDEX(Metodo!$C$39:$C$41,MATCH($K7,Metodo!$B$39:$B$41,0)),0)) | M7: =IF($L7="","",IF($L7>=Metodo!$C$43,"A",IF($L7>=Metodo!$C$44,"B","C"))) | N7: Nao contatado | Q7: Primeiro contato | T7: Tier 1 (varredura TomTom 2026-08-29, PR #185). Qualificacao: site proprio. ATENCAO: parece rede com 3+ unidades (Bosque Maia, Vila Guilherme, Freguesia, possivelmente mais - o mesmo telefone aparece tambem no Tier 2 como "CrossFit Saurus" em Vila Guilherme). Regra do script (secao 6) desqualifica rede com mais de 3 unidades na Fase 1 - confirmar com Renan antes de abordar; se confirmado, marcar Descartado.
A8: =IF($B8="","",ROW()-1) | B8: CrossFit Vila Augusta | C8: Guarulhos - Vila Augusta | D8: @crossfitvilaaugusta | E8: +55 11 93022-9182 | K8: Grande SP | L8: =IF($B8="","",IF($F8="",Metodo!$C$30,IF(AND($F8>=80,$F8<=250),Metodo!$C$28,IF(OR(AND($F8>=40,$F8<=79),AND($F8>=251,$F8<=400)),Metodo!$C$29,Metodo!$C$30)))+IFERROR(INDEX(Metodo!$C$32:$C$35,MATCH($G8,Metodo!$B$32:$B$35,0)),0)+COUNTIF($H8:$J8,"Sim")*Metodo!$C$37+IFERROR(INDEX(Metodo!$C$39:$C$41,MATCH($K8,Metodo!$B$39:$B$41,0)),0)) | M8: =IF($L8="","",IF($L8>=Metodo!$C$43,"A",IF($L8>=Metodo!$C$44,"B","C"))) | N8: Nao contatado | Q8: Primeiro contato | T8: Tier 1 (varredura TomTom 2026-08-29, PR #185). Qualificacao: afiliado oficial. Instagram @crossfitvilaaugusta, 1,2 mil seguidores. Comunidade bem ativa: aulao de dia dos pais, churrasco do box, musica ao vivo - perfil familiar/comunitario forte.
A9: =IF($B9="","",ROW()-1) | B9: Crossfit GRU | C9: Guarulhos - Vila Augusta | D9: @cf_gru | E9: +55 11 97246-7271 | K9: Grande SP | L9: =IF($B9="","",IF($F9="",Metodo!$C$30,IF(AND($F9>=80,$F9<=250),Metodo!$C$28,IF(OR(AND($F9>=40,$F9<=79),AND($F9>=251,$F9<=400)),Metodo!$C$29,Metodo!$C$30)))+IFERROR(INDEX(Metodo!$C$32:$C$35,MATCH($G9,Metodo!$B$32:$B$35,0)),0)+COUNTIF($H9:$J9,"Sim")*Metodo!$C$37+IFERROR(INDEX(Metodo!$C$39:$C$41,MATCH($K9,Metodo!$B$39:$B$41,0)),0)) | M9: =IF($L9="","",IF($L9>=Metodo!$C$43,"A",IF($L9>=Metodo!$C$44,"B","C"))) | N9: Nao contatado | Q9: Primeiro contato | T9: Tier 1 (varredura TomTom 2026-08-29, PR #185). Qualificacao: site proprio. Instagram @cf_gru, 6,1 mil seguidores, 8+ anos de historia. Posta o WOD do dia no feed regularmente (sinal direto da Variante A do script). Tem e-mail proprio (contato@crossfitgru.com).
A10: =IF($B10="","",ROW()-1) | B10: CrossFit Barueri | C10: Barueri - Alphaville | E10: +55 11 97503-7921 | K10: Grande SP | L10: =IF($B10="","",IF($F10="",Metodo!$C$30,IF(AND($F10>=80,$F10<=250),Metodo!$C$28,IF(OR(AND($F10>=40,$F10<=79),AND($F10>=251,$F10<=400)),Metodo!$C$29,Metodo!$C$30)))+IFERROR(INDEX(Metodo!$C$32:$C$35,MATCH($G10,Metodo!$B$32:$B$35,0)),0)+COUNTIF($H10:$J10,"Sim")*Metodo!$C$37+IFERROR(INDEX(Metodo!$C$39:$C$41,MATCH($K10,Metodo!$B$39:$B$41,0)),0)) | M10: =IF($L10="","",IF($L10>=Metodo!$C$43,"A",IF($L10>=Metodo!$C$44,"B","C"))) | N10: Nao contatado | Q10: Primeiro contato | T10: Tier 2 (varredura TomTom 2026-08-29, PR #185). Qualificacao: afiliado oficial.
A11: =IF($B11="","",ROW()-1) | B11: CrossFit Rudge Ramos | C11: São Bernardo do Campo - Anchieta | K11: Grande SP | L11: =IF($B11="","",IF($F11="",Metodo!$C$30,IF(AND($F11>=80,$F11<=250),Metodo!$C$28,IF(OR(AND($F11>=40,$F11<=79),AND($F11>=251,$F11<=400)),Metodo!$C$29,Metodo!$C$30)))+IFERROR(INDEX(Metodo!$C$32:$C$35,MATCH($G11,Metodo!$B$32:$B$35,0)),0)+COUNTIF($H11:$J11,"Sim")*Metodo!$C$37+IFERROR(INDEX(Metodo!$C$39:$C$41,MATCH($K11,Metodo!$B$39:$B$41,0)),0)) | M11: =IF($L11="","",IF($L11>=Metodo!$C$43,"A",IF($L11>=Metodo!$C$44,"B","C"))) | N11: Nao contatado | Q11: Achar contato | T11: Tier 2 (varredura TomTom 2026-08-29, PR #185). Qualificacao: afiliado oficial.
A12: =IF($B12="","",ROW()-1) | B12: Soren CrossFit | C12: São Bernardo do Campo - Anchieta | E12: +55 11 95941-3662 | K12: Grande SP | L12: =IF($B12="","",IF($F12="",Metodo!$C$30,IF(AND($F12>=80,$F12<=250),Metodo!$C$28,IF(OR(AND($F12>=40,$F12<=79),AND($F12>=251,$F12<=400)),Metodo!$C$29,Metodo!$C$30)))+IFERROR(INDEX(Metodo!$C$32:$C$35,MATCH($G12,Metodo!$B$32:$B$35,0)),0)+COUNTIF($H12:$J12,"Sim")*Metodo!$C$37+IFERROR(INDEX(Metodo!$C$39:$C$41,MATCH($K12,Metodo!$B$39:$B$41,0)),0)) | M12: =IF($L12="","",IF($L12>=Metodo!$C$43,"A",IF($L12>=Metodo!$C$44,"B","C"))) | N12: Nao contatado | Q12: Primeiro contato | T12: Tier 2 (varredura TomTom 2026-08-29, PR #185). Qualificacao: afiliado oficial.
A13: =IF($B13="","",ROW()-1) | B13: B4thor CrossFit | C13: São Paulo - Campo Belo | E13: +55 11 98244-0880 | K13: Grande SP | L13: =IF($B13="","",IF($F13="",Metodo!$C$30,IF(AND($F13>=80,$F13<=250),Metodo!$C$28,IF(OR(AND($F13>=40,$F13<=79),AND($F13>=251,$F13<=400)),Metodo!$C$29,Metodo!$C$30)))+IFERROR(INDEX(Metodo!$C$32:$C$35,MATCH($G13,Metodo!$B$32:$B$35,0)),0)+COUNTIF($H13:$J13,"Sim")*Metodo!$C$37+IFERROR(INDEX(Metodo!$C$39:$C$41,MATCH($K13,Metodo!$B$39:$B$41,0)),0)) | M13: =IF($L13="","",IF($L13>=Metodo!$C$43,"A",IF($L13>=Metodo!$C$44,"B","C"))) | N13: Nao contatado | Q13: Primeiro contato | T13: Tier 2 (varredura TomTom 2026-08-29, PR #185). Qualificacao: afiliado oficial.
A14: =IF($B14="","",ROW()-1) | B14: CrossFit | C14: São Paulo - Pinheiros | E14: +55 11 97358-5345 | K14: Grande SP | L14: =IF($B14="","",IF($F14="",Metodo!$C$30,IF(AND($F14>=80,$F14<=250),Metodo!$C$28,IF(OR(AND($F14>=40,$F14<=79),AND($F14>=251,$F14<=400)),Metodo!$C$29,Metodo!$C$30)))+IFERROR(INDEX(Metodo!$C$32:$C$35,MATCH($G14,Metodo!$B$32:$B$35,0)),0)+COUNTIF($H14:$J14,"Sim")*Metodo!$C$37+IFERROR(INDEX(Metodo!$C$39:$C$41,MATCH($K14,Metodo!$B$39:$B$41,0)),0)) | M14: =IF($L14="","",IF($L14>=Metodo!$C$43,"A",IF($L14>=Metodo!$C$44,"B","C"))) | N14: Nao contatado | Q14: Primeiro contato | T14: Tier 2 (varredura TomTom 2026-08-29, PR #185). Qualificacao: afiliado oficial.
A15: =IF($B15="","",ROW()-1) | B15: CrossFit Azteca | C15: São Paulo - Santo Amaro | E15: +55 11 97205-9595 | K15: Grande SP | L15: =IF($B15="","",IF($F15="",Metodo!$C$30,IF(AND($F15>=80,$F15<=250),Metodo!$C$28,IF(OR(AND($F15>=40,$F15<=79),AND($F15>=251,$F15<=400)),Metodo!$C$29,Metodo!$C$30)))+IFERROR(INDEX(Metodo!$C$32:$C$35,MATCH($G15,Metodo!$B$32:$B$35,0)),0)+COUNTIF($H15:$J15,"Sim")*Metodo!$C$37+IFERROR(INDEX(Metodo!$C$39:$C$41,MATCH($K15,Metodo!$B$39:$B$41,0)),0)) | M15: =IF($L15="","",IF($L15>=Metodo!$C$43,"A",IF($L15>=Metodo!$C$44,"B","C"))) | N15: Nao contatado | Q15: Primeiro contato | T15: Tier 2 (varredura TomTom 2026-08-29, PR #185). Qualificacao: afiliado oficial.
A16: =IF($B16="","",ROW()-1) | B16: CrossFit Batalha | C16: São Paulo - Jacana | D16: @crossfitbatalha | E16: +55 11 94037-4949 | K16: Grande SP | L16: =IF($B16="","",IF($F16="",Metodo!$C$30,IF(AND($F16>=80,$F16<=250),Metodo!$C$28,IF(OR(AND($F16>=40,$F16<=79),AND($F16>=251,$F16<=400)),Metodo!$C$29,Metodo!$C$30)))+IFERROR(INDEX(Metodo!$C$32:$C$35,MATCH($G16,Metodo!$B$32:$B$35,0)),0)+COUNTIF($H16:$J16,"Sim")*Metodo!$C$37+IFERROR(INDEX(Metodo!$C$39:$C$41,MATCH($K16,Metodo!$B$39:$B$41,0)),0)) | M16: =IF($L16="","",IF($L16>=Metodo!$C$43,"A",IF($L16>=Metodo!$C$44,"B","C"))) | N16: Nao contatado | Q16: Primeiro contato | T16: Tier 2 (varredura TomTom 2026-08-29, PR #185). Qualificacao: afiliado oficial. Instagram @crossfitbatalha, 3,7 mil seguidores, Jacana/zona norte. Posiciona "CrossFit e para TODOS" e agenda aula experimental direto pelo Instagram - fluxo de agendamento manual.
A17: =IF($B17="","",ROW()-1) | B17: CrossFit Beco | C17: São Paulo - Vila Leopoldina | E17: +55 11 95240-4007 | K17: Grande SP | L17: =IF($B17="","",IF($F17="",Metodo!$C$30,IF(AND($F17>=80,$F17<=250),Metodo!$C$28,IF(OR(AND($F17>=40,$F17<=79),AND($F17>=251,$F17<=400)),Metodo!$C$29,Metodo!$C$30)))+IFERROR(INDEX(Metodo!$C$32:$C$35,MATCH($G17,Metodo!$B$32:$B$35,0)),0)+COUNTIF($H17:$J17,"Sim")*Metodo!$C$37+IFERROR(INDEX(Metodo!$C$39:$C$41,MATCH($K17,Metodo!$B$39:$B$41,0)),0)) | M17: =IF($L17="","",IF($L17>=Metodo!$C$43,"A",IF($L17>=Metodo!$C$44,"B","C"))) | N17: Nao contatado | Q17: Primeiro contato | T17: Tier 2 (varredura TomTom 2026-08-29, PR #185). Qualificacao: afiliado oficial.
A18: =IF($B18="","",ROW()-1) | B18: CrossFit Betta | C18: São Paulo - Mandaqui | D18: @crossfitbetta | E18: +55 11 2281-9110 | K18: Grande SP | L18: =IF($B18="","",IF($F18="",Metodo!$C$30,IF(AND($F18>=80,$F18<=250),Metodo!$C$28,IF(OR(AND($F18>=40,$F18<=79),AND($F18>=251,$F18<=400)),Metodo!$C$29,Metodo!$C$30)))+IFERROR(INDEX(Metodo!$C$32:$C$35,MATCH($G18,Metodo!$B$32:$B$35,0)),0)+COUNTIF($H18:$J18,"Sim")*Metodo!$C$37+IFERROR(INDEX(Metodo!$C$39:$C$41,MATCH($K18,Metodo!$B$39:$B$41,0)),0)) | M18: =IF($L18="","",IF($L18>=Metodo!$C$43,"A",IF($L18>=Metodo!$C$44,"B","C"))) | N18: Nao contatado | Q18: Primeiro contato | T18: Tier 2 (varredura TomTom 2026-08-29, PR #185). Qualificacao: afiliado oficial. Instagram @crossfitbetta, quase 4 mil seguidores, Mandaqui. Posicionamento de bem-estar ("saude fisica e mental", "mais que uma academia").
A19: =IF($B19="","",ROW()-1) | B19: CrossFit Bronx | C19: São Paulo - Itaim Bibi | E19: +55 11 99292-6136 | K19: Grande SP | L19: =IF($B19="","",IF($F19="",Metodo!$C$30,IF(AND($F19>=80,$F19<=250),Metodo!$C$28,IF(OR(AND($F19>=40,$F19<=79),AND($F19>=251,$F19<=400)),Metodo!$C$29,Metodo!$C$30)))+IFERROR(INDEX(Metodo!$C$32:$C$35,MATCH($G19,Metodo!$B$32:$B$35,0)),0)+COUNTIF($H19:$J19,"Sim")*Metodo!$C$37+IFERROR(INDEX(Metodo!$C$39:$C$41,MATCH($K19,Metodo!$B$39:$B$41,0)),0)) | M19: =IF($L19="","",IF($L19>=Metodo!$C$43,"A",IF($L19>=Metodo!$C$44,"B","C"))) | N19: Nao contatado | Q19: Primeiro contato | T19: Tier 2 (varredura TomTom 2026-08-29, PR #185). Qualificacao: afiliado oficial.
A20: =IF($B20="","",ROW()-1) | B20: CrossFit Campo Bacharel | C20: São Paulo - Campo Belo | E20: +55 11 2397-0779 | K20: Grande SP | L20: =IF($B20="","",IF($F20="",Metodo!$C$30,IF(AND($F20>=80,$F20<=250),Metodo!$C$28,IF(OR(AND($F20>=40,$F20<=79),AND($F20>=251,$F20<=400)),Metodo!$C$29,Metodo!$C$30)))+IFERROR(INDEX(Metodo!$C$32:$C$35,MATCH($G20,Metodo!$B$32:$B$35,0)),0)+COUNTIF($H20:$J20,"Sim")*Metodo!$C$37+IFERROR(INDEX(Metodo!$C$39:$C$41,MATCH($K20,Metodo!$B$39:$B$41,0)),0)) | M20: =IF($L20="","",IF($L20>=Metodo!$C$43,"A",IF($L20>=Metodo!$C$44,"B","C"))) | N20: Nao contatado | Q20: Primeiro contato | T20: Tier 2 (varredura TomTom 2026-08-29, PR #185). Qualificacao: afiliado oficial.
A21: =IF($B21="","",ROW()-1) | B21: CrossFit City Wolves | C21: São Paulo - Saúde | E21: +55 11 99358-0631 | K21: Grande SP | L21: =IF($B21="","",IF($F21="",Metodo!$C$30,IF(AND($F21>=80,$F21<=250),Metodo!$C$28,IF(OR(AND($F21>=40,$F21<=79),AND($F21>=251,$F21<=400)),Metodo!$C$29,Metodo!$C$30)))+IFERROR(INDEX(Metodo!$C$32:$C$35,MATCH($G21,Metodo!$B$32:$B$35,0)),0)+COUNTIF($H21:$J21,"Sim")*Metodo!$C$37+IFERROR(INDEX(Metodo!$C$39:$C$41,MATCH($K21,Metodo!$B$39:$B$41,0)),0)) | M21: =IF($L21="","",IF($L21>=Metodo!$C$43,"A",IF($L21>=Metodo!$C$44,"B","C"))) | N21: Nao contatado | Q21: Primeiro contato | T21: Tier 2 (varredura TomTom 2026-08-29, PR #185). Qualificacao: afiliado oficial.
A22: =IF($B22="","",ROW()-1) | B22: CrossFit Conceição | C22: São Paulo - Jabaquara | E22: +55 11 5017-7283 | K22: Grande SP | L22: =IF($B22="","",IF($F22="",Metodo!$C$30,IF(AND($F22>=80,$F22<=250),Metodo!$C$28,IF(OR(AND($F22>=40,$F22<=79),AND($F22>=251,$F22<=400)),Metodo!$C$29,Metodo!$C$30)))+IFERROR(INDEX(Metodo!$C$32:$C$35,MATCH($G22,Metodo!$B$32:$B$35,0)),0)+COUNTIF($H22:$J22,"Sim")*Metodo!$C$37+IFERROR(INDEX(Metodo!$C$39:$C$41,MATCH($K22,Metodo!$B$39:$B$41,0)),0)) | M22: =IF($L22="","",IF($L22>=Metodo!$C$43,"A",IF($L22>=Metodo!$C$44,"B","C"))) | N22: Nao contatado | Q22: Primeiro contato | T22: Tier 2 (varredura TomTom 2026-08-29, PR #185). Qualificacao: afiliado oficial.
A23: =IF($B23="","",ROW()-1) | B23: CrossFit Fire Hawks | C23: São Paulo - Vila Mariana | E23: +55 11 96609-2246 | K23: Grande SP | L23: =IF($B23="","",IF($F23="",Metodo!$C$30,IF(AND($F23>=80,$F23<=250),Metodo!$C$28,IF(OR(AND($F23>=40,$F23<=79),AND($F23>=251,$F23<=400)),Metodo!$C$29,Metodo!$C$30)))+IFERROR(INDEX(Metodo!$C$32:$C$35,MATCH($G23,Metodo!$B$32:$B$35,0)),0)+COUNTIF($H23:$J23,"Sim")*Metodo!$C$37+IFERROR(INDEX(Metodo!$C$39:$C$41,MATCH($K23,Metodo!$B$39:$B$41,0)),0)) | M23: =IF($L23="","",IF($L23>=Metodo!$C$43,"A",IF($L23>=Metodo!$C$44,"B","C"))) | N23: Nao contatado | Q23: Primeiro contato | T23: Tier 2 (varredura TomTom 2026-08-29, PR #185). Qualificacao: afiliado oficial.
A24: =IF($B24="","",ROW()-1) | B24: CrossFit Four Heads | C24: São Paulo - Saúde | E24: +55 11 99170-7922 | K24: Grande SP | L24: =IF($B24="","",IF($F24="",Metodo!$C$30,IF(AND($F24>=80,$F24<=250),Metodo!$C$28,IF(OR(AND($F24>=40,$F24<=79),AND($F24>=251,$F24<=400)),Metodo!$C$29,Metodo!$C$30)))+IFERROR(INDEX(Metodo!$C$32:$C$35,MATCH($G24,Metodo!$B$32:$B$35,0)),0)+COUNTIF($H24:$J24,"Sim")*Metodo!$C$37+IFERROR(INDEX(Metodo!$C$39:$C$41,MATCH($K24,Metodo!$B$39:$B$41,0)),0)) | M24: =IF($L24="","",IF($L24>=Metodo!$C$43,"A",IF($L24>=Metodo!$C$44,"B","C"))) | N24: Nao contatado | Q24: Primeiro contato | T24: Tier 2 (varredura TomTom 2026-08-29, PR #185). Qualificacao: afiliado oficial.
A25: =IF($B25="","",ROW()-1) | B25: CrossFit Higienópolis | C25: São Paulo - Consolação | E25: +55 11 96336-6412 | K25: Grande SP | L25: =IF($B25="","",IF($F25="",Metodo!$C$30,IF(AND($F25>=80,$F25<=250),Metodo!$C$28,IF(OR(AND($F25>=40,$F25<=79),AND($F25>=251,$F25<=400)),Metodo!$C$29,Metodo!$C$30)))+IFERROR(INDEX(Metodo!$C$32:$C$35,MATCH($G25,Metodo!$B$32:$B$35,0)),0)+COUNTIF($H25:$J25,"Sim")*Metodo!$C$37+IFERROR(INDEX(Metodo!$C$39:$C$41,MATCH($K25,Metodo!$B$39:$B$41,0)),0)) | M25: =IF($L25="","",IF($L25>=Metodo!$C$43,"A",IF($L25>=Metodo!$C$44,"B","C"))) | N25: Nao contatado | Q25: Primeiro contato | T25: Tier 2 (varredura TomTom 2026-08-29, PR #185). Qualificacao: afiliado oficial.
A26: =IF($B26="","",ROW()-1) | B26: CrossFit Juntos | C26: São Paulo - Itaim Bibi | E26: +55 11 99947-5785 | K26: Grande SP | L26: =IF($B26="","",IF($F26="",Metodo!$C$30,IF(AND($F26>=80,$F26<=250),Metodo!$C$28,IF(OR(AND($F26>=40,$F26<=79),AND($F26>=251,$F26<=400)),Metodo!$C$29,Metodo!$C$30)))+IFERROR(INDEX(Metodo!$C$32:$C$35,MATCH($G26,Metodo!$B$32:$B$35,0)),0)+COUNTIF($H26:$J26,"Sim")*Metodo!$C$37+IFERROR(INDEX(Metodo!$C$39:$C$41,MATCH($K26,Metodo!$B$39:$B$41,0)),0)) | M26: =IF($L26="","",IF($L26>=Metodo!$C$43,"A",IF($L26>=Metodo!$C$44,"B","C"))) | N26: Nao contatado | Q26: Primeiro contato | T26: Tier 2 (varredura TomTom 2026-08-29, PR #185). Qualificacao: afiliado oficial.
A27: =IF($B27="","",ROW()-1) | B27: CrossFit Rutilo | C27: São Paulo - Lapa | E27: +55 11 94390-7851 | K27: Grande SP | L27: =IF($B27="","",IF($F27="",Metodo!$C$30,IF(AND($F27>=80,$F27<=250),Metodo!$C$28,IF(OR(AND($F27>=40,$F27<=79),AND($F27>=251,$F27<=400)),Metodo!$C$29,Metodo!$C$30)))+IFERROR(INDEX(Metodo!$C$32:$C$35,MATCH($G27,Metodo!$B$32:$B$35,0)),0)+COUNTIF($H27:$J27,"Sim")*Metodo!$C$37+IFERROR(INDEX(Metodo!$C$39:$C$41,MATCH($K27,Metodo!$B$39:$B$41,0)),0)) | M27: =IF($L27="","",IF($L27>=Metodo!$C$43,"A",IF($L27>=Metodo!$C$44,"B","C"))) | N27: Nao contatado | Q27: Primeiro contato | T27: Tier 2 (varredura TomTom 2026-08-29, PR #185). Qualificacao: afiliado oficial.
A28: =IF($B28="","",ROW()-1) | B28: CrossFit Saga | C28: São Paulo - Vila Mariana | E28: +55 11 97349-2008 | K28: Grande SP | L28: =IF($B28="","",IF($F28="",Metodo!$C$30,IF(AND($F28>=80,$F28<=250),Metodo!$C$28,IF(OR(AND($F28>=40,$F28<=79),AND($F28>=251,$F28<=400)),Metodo!$C$29,Metodo!$C$30)))+IFERROR(INDEX(Metodo!$C$32:$C$35,MATCH($G28,Metodo!$B$32:$B$35,0)),0)+COUNTIF($H28:$J28,"Sim")*Metodo!$C$37+IFERROR(INDEX(Metodo!$C$39:$C$41,MATCH($K28,Metodo!$B$39:$B$41,0)),0)) | M28: =IF($L28="","",IF($L28>=Metodo!$C$43,"A",IF($L28>=Metodo!$C$44,"B","C"))) | N28: Nao contatado | Q28: Primeiro contato | T28: Tier 2 (varredura TomTom 2026-08-29, PR #185). Qualificacao: afiliado oficial.
A29: =IF($B29="","",ROW()-1) | B29: CrossFit Saurus | C29: São Paulo - Vila Guilherme | E29: +55 11 98254-0787 | K29: Grande SP | L29: =IF($B29="","",IF($F29="",Metodo!$C$30,IF(AND($F29>=80,$F29<=250),Metodo!$C$28,IF(OR(AND($F29>=40,$F29<=79),AND($F29>=251,$F29<=400)),Metodo!$C$29,Metodo!$C$30)))+IFERROR(INDEX(Metodo!$C$32:$C$35,MATCH($G29,Metodo!$B$32:$B$35,0)),0)+COUNTIF($H29:$J29,"Sim")*Metodo!$C$37+IFERROR(INDEX(Metodo!$C$39:$C$41,MATCH($K29,Metodo!$B$39:$B$41,0)),0)) | M29: =IF($L29="","",IF($L29>=Metodo!$C$43,"A",IF($L29>=Metodo!$C$44,"B","C"))) | N29: Nao contatado | Q29: Primeiro contato | T29: Tier 2 (varredura TomTom 2026-08-29, PR #185). Qualificacao: afiliado oficial.
A30: =IF($B30="","",ROW()-1) | B30: CrossFit São Francisco | C30: São Paulo - Jaguaré | E30: +55 11 97306-6942 | K30: Grande SP | L30: =IF($B30="","",IF($F30="",Metodo!$C$30,IF(AND($F30>=80,$F30<=250),Metodo!$C$28,IF(OR(AND($F30>=40,$F30<=79),AND($F30>=251,$F30<=400)),Metodo!$C$29,Metodo!$C$30)))+IFERROR(INDEX(Metodo!$C$32:$C$35,MATCH($G30,Metodo!$B$32:$B$35,0)),0)+COUNTIF($H30:$J30,"Sim")*Metodo!$C$37+IFERROR(INDEX(Metodo!$C$39:$C$41,MATCH($K30,Metodo!$B$39:$B$41,0)),0)) | M30: =IF($L30="","",IF($L30>=Metodo!$C$43,"A",IF($L30>=Metodo!$C$44,"B","C"))) | N30: Nao contatado | Q30: Primeiro contato | T30: Tier 2 (varredura TomTom 2026-08-29, PR #185). Qualificacao: afiliado oficial.
... A54: =IF($B54="","",ROW()-1) | B54: Box Utinga Crossfit | C54: Santo André - Vila Metalúrgica | E54: +55 11 4997-3228 | K54: Grande SP | L54: =IF($B54="","",IF($F54="",Metodo!$C$30,IF(AND($F54>=80,$F54<=250),Metodo!$C$28,IF(OR(AND($F54>=40,$F54<=79),AND($F54>=251,$F54<=400)),Metodo!$C$29,Metodo!$C$30)))+IFERROR(INDEX(Metodo!$C$32:$C$35,MATCH($G54,Metodo!$B$32:$B$35,0)),0)+COUNTIF($H54:$J54,"Sim")*Metodo!$C$37+IFERROR(INDEX(Metodo!$C$39:$C$41,MATCH($K54,Metodo!$B$39:$B$41,0)),0)) | M54: =IF($L54="","",IF($L54>=Metodo!$C$43,"A",IF($L54>=Metodo!$C$44,"B","C"))) | N54: Nao contatado | Q54: Primeiro contato | T54: Tier 3 (varredura TomTom 2026-08-29, PR #185). Qualificacao: site próprio.
A55: =IF($B55="","",ROW()-1) | B55: Crossfit 198 | C55: Santo André - Bairro Jardim | K55: Grande SP | L55: =IF($B55="","",IF($F55="",Metodo!$C$30,IF(AND($F55>=80,$F55<=250),Metodo!$C$28,IF(OR(AND($F55>=40,$F55<=79),AND($F55>=251,$F55<=400)),Metodo!$C$29,Metodo!$C$30)))+IFERROR(INDEX(Metodo!$C$32:$C$35,MATCH($G55,Metodo!$B$32:$B$35,0)),0)+COUNTIF($H55:$J55,"Sim")*Metodo!$C$37+IFERROR(INDEX(Metodo!$C$39:$C$41,MATCH($K55,Metodo!$B$39:$B$41,0)),0)) | M55: =IF($L55="","",IF($L55>=Metodo!$C$43,"A",IF($L55>=Metodo!$C$44,"B","C"))) | N55: Nao contatado | Q55: Achar contato | T55: Tier 3 (varredura TomTom 2026-08-29, PR #185). Qualificacao: sem site.
A56: =IF($B56="","",ROW()-1) | B56: Crossfit Badak | C56: Santo André - Centro | E56: +55 11 4432-2332 | K56: Grande SP | L56: =IF($B56="","",IF($F56="",Metodo!$C$30,IF(AND($F56>=80,$F56<=250),Metodo!$C$28,IF(OR(AND($F56>=40,$F56<=79),AND($F56>=251,$F56<=400)),Metodo!$C$29,Metodo!$C$30)))+IFERROR(INDEX(Metodo!$C$32:$C$35,MATCH($G56,Metodo!$B$32:$B$35,0)),0)+COUNTIF($H56:$J56,"Sim")*Metodo!$C$37+IFERROR(INDEX(Metodo!$C$39:$C$41,MATCH($K56,Metodo!$B$39:$B$41,0)),0)) | M56: =IF($L56="","",IF($L56>=Metodo!$C$43,"A",IF($L56>=Metodo!$C$44,"B","C"))) | N56: Nao contatado | Q56: Primeiro contato | T56: Tier 3 (varredura TomTom 2026-08-29, PR #185). Qualificacao: site próprio.
A57: =IF($B57="","",ROW()-1) | B57: Juscelino Kubitschek Crossfit | C57: Santo André - Bairro Jardim | E57: +55 11 2896-0253 | K57: Grande SP | L57: =IF($B57="","",IF($F57="",Metodo!$C$30,IF(AND($F57>=80,$F57<=250),Metodo!$C$28,IF(OR(AND($F57>=40,$F57<=79),AND($F57>=251,$F57<=400)),Metodo!$C$29,Metodo!$C$30)))+IFERROR(INDEX(Metodo!$C$32:$C$35,MATCH($G57,Metodo!$B$32:$B$35,0)),0)+COUNTIF($H57:$J57,"Sim")*Metodo!$C$37+IFERROR(INDEX(Metodo!$C$39:$C$41,MATCH($K57,Metodo!$B$39:$B$41,0)),0)) | M57: =IF($L57="","",IF($L57>=Metodo!$C$43,"A",IF($L57>=Metodo!$C$44,"B","C"))) | N57: Nao contatado | Q57: Primeiro contato | T57: Tier 3 (varredura TomTom 2026-08-29, PR #185). Qualificacao: sem site.
A58: =IF($B58="","",ROW()-1) | B58: Cross Planalto | C58: São Bernardo do Campo - Independência | E58: +55 11 4509-9888 | K58: Grande SP | L58: =IF($B58="","",IF($F58="",Metodo!$C$30,IF(AND($F58>=80,$F58<=250),Metodo!$C$28,IF(OR(AND($F58>=40,$F58<=79),AND($F58>=251,$F58<=400)),Metodo!$C$29,Metodo!$C$30)))+IFERROR(INDEX(Metodo!$C$32:$C$35,MATCH($G58,Metodo!$B$32:$B$35,0)),0)+COUNTIF($H58:$J58,"Sim")*Metodo!$C$37+IFERROR(INDEX(Metodo!$C$39:$C$41,MATCH($K58,Metodo!$B$39:$B$41,0)),0)) | M58: =IF($L58="","",IF($L58>=Metodo!$C$43,"A",IF($L58>=Metodo!$C$44,"B","C"))) | N58: Nao contatado | Q58: Primeiro contato | T58: Tier 3 (varredura TomTom 2026-08-29, PR #185). Qualificacao: site próprio.
A59: =IF($B59="","",ROW()-1) | B59: CrossFit Range | C59: São Bernardo do Campo - Baeta Neves | K59: Grande SP | L59: =IF($B59="","",IF($F59="",Metodo!$C$30,IF(AND($F59>=80,$F59<=250),Metodo!$C$28,IF(OR(AND($F59>=40,$F59<=79),AND($F59>=251,$F59<=400)),Metodo!$C$29,Metodo!$C$30)))+IFERROR(INDEX(Metodo!$C$32:$C$35,MATCH($G59,Metodo!$B$32:$B$35,0)),0)+COUNTIF($H59:$J59,"Sim")*Metodo!$C$37+IFERROR(INDEX(Metodo!$C$39:$C$41,MATCH($K59,Metodo!$B$39:$B$41,0)),0)) | M59: =IF($L59="","",IF($L59>=Metodo!$C$43,"A",IF($L59>=Metodo!$C$44,"B","C"))) | N59: Nao contatado | Q59: Achar contato | T59: Tier 3 (varredura TomTom 2026-08-29, PR #185). Qualificacao: site próprio.
A60: =IF($B60="","",ROW()-1) | B60: CrossFit Titânio | C60: São Bernardo do Campo - Centro | E60: +55 11 3380-6506 | K60: Grande SP | L60: =IF($B60="","",IF($F60="",Metodo!$C$30,IF(AND($F60>=80,$F60<=250),Metodo!$C$28,IF(OR(AND($F60>=40,$F60<=79),AND($F60>=251,$F60<=400)),Metodo!$C$29,Metodo!$C$30)))+IFERROR(INDEX(Metodo!$C$32:$C$35,MATCH($G60,Metodo!$B$32:$B$35,0)),0)+COUNTIF($H60:$J60,"Sim")*Metodo!$C$37+IFERROR(INDEX(Metodo!$C$39:$C$41,MATCH($K60,Metodo!$B$39:$B$41,0)),0)) | M60: =IF($L60="","",IF($L60>=Metodo!$C$43,"A",IF($L60>=Metodo!$C$44,"B","C"))) | N60: Nao contatado | Q60: Primeiro contato | T60: Tier 3 (varredura TomTom 2026-08-29, PR #185). Qualificacao: site próprio.
A61: =IF($B61="","",ROW()-1) | B61: Crossfit Capitão | C61: São Bernardo do Campo - Casa | E61: +55 11 4509-5333 | K61: Grande SP | L61: =IF($B61="","",IF($F61="",Metodo!$C$30,IF(AND($F61>=80,$F61<=250),Metodo!$C$28,IF(OR(AND($F61>=40,$F61<=79),AND($F61>=251,$F61<=400)),Metodo!$C$29,Metodo!$C$30)))+IFERROR(INDEX(Metodo!$C$32:$C$35,MATCH($G61,Metodo!$B$32:$B$35,0)),0)+COUNTIF($H61:$J61,"Sim")*Metodo!$C$37+IFERROR(INDEX(Metodo!$C$39:$C$41,MATCH($K61,Metodo!$B$39:$B$41,0)),0)) | M61: =IF($L61="","",IF($L61>=Metodo!$C$43,"A",IF($L61>=Metodo!$C$44,"B","C"))) | N61: Nao contatado | Q61: Primeiro contato | T61: Tier 3 (varredura TomTom 2026-08-29, PR #185). Qualificacao: sem site.
A62: =IF($B62="","",ROW()-1) | B62: Crossfit Tamoko | C62: São Bernardo do Campo - Rudge Ramos | E62: +55 11 99664-7999 | K62: Grande SP | L62: =IF($B62="","",IF($F62="",Metodo!$C$30,IF(AND($F62>=80,$F62<=250),Metodo!$C$28,IF(OR(AND($F62>=40,$F62<=79),AND($F62>=251,$F62<=400)),Metodo!$C$29,Metodo!$C$30)))+IFERROR(INDEX(Metodo!$C$32:$C$35,MATCH($G62,Metodo!$B$32:$B$35,0)),0)+COUNTIF($H62:$J62,"Sim")*Metodo!$C$37+IFERROR(INDEX(Metodo!$C$39:$C$41,MATCH($K62,Metodo!$B$39:$B$41,0)),0)) | M62: =IF($L62="","",IF($L62>=Metodo!$C$43,"A",IF($L62>=Metodo!$C$44,"B","C"))) | N62: Nao contatado | Q62: Primeiro contato | T62: Tier 3 (varredura TomTom 2026-08-29, PR #185). Qualificacao: sem site.
A63: =IF($B63="","",ROW()-1) | B63: Crossfit Voraz | C63: São Bernardo do Campo - Centro | E63: +55 11 97698-1669 | K63: Grande SP | L63: =IF($B63="","",IF($F63="",Metodo!$C$30,IF(AND($F63>=80,$F63<=250),Metodo!$C$28,IF(OR(AND($F63>=40,$F63<=79),AND($F63>=251,$F63<=400)),Metodo!$C$29,Metodo!$C$30)))+IFERROR(INDEX(Metodo!$C$32:$C$35,MATCH($G63,Metodo!$B$32:$B$35,0)),0)+COUNTIF($H63:$J63,"Sim")*Metodo!$C$37+IFERROR(INDEX(Metodo!$C$39:$C$41,MATCH($K63,Metodo!$B$39:$B$41,0)),0)) | M63: =IF($L63="","",IF($L63>=Metodo!$C$43,"A",IF($L63>=Metodo!$C$44,"B","C"))) | N63: Nao contatado | Q63: Primeiro contato | T63: Tier 3 (varredura TomTom 2026-08-29, PR #185). Qualificacao: site próprio.
A64: =IF($B64="","",ROW()-1) | B64: Arena Crossfit III | C64: São Caetano do Sul - Ceramica | E64: +55 11 96747-7124 | K64: Grande SP | L64: =IF($B64="","",IF($F64="",Metodo!$C$30,IF(AND($F64>=80,$F64<=250),Metodo!$C$28,IF(OR(AND($F64>=40,$F64<=79),AND($F64>=251,$F64<=400)),Metodo!$C$29,Metodo!$C$30)))+IFERROR(INDEX(Metodo!$C$32:$C$35,MATCH($G64,Metodo!$B$32:$B$35,0)),0)+COUNTIF($H64:$J64,"Sim")*Metodo!$C$37+IFERROR(INDEX(Metodo!$C$39:$C$41,MATCH($K64,Metodo!$B$39:$B$41,0)),0)) | M64: =IF($L64="","",IF($L64>=Metodo!$C$43,"A",IF($L64>=Metodo!$C$44,"B","C"))) | N64: Nao contatado | Q64: Primeiro contato | T64: Tier 3 (varredura TomTom 2026-08-29, PR #185). Qualificacao: sem site.
A65: =IF($B65="","",ROW()-1) | B65: CrossFit Barcelona Park | C65: São Caetano do Sul - Santa Maria | E65: +55 11 93055-4440 | K65: Grande SP | L65: =IF($B65="","",IF($F65="",Metodo!$C$30,IF(AND($F65>=80,$F65<=250),Metodo!$C$28,IF(OR(AND($F65>=40,$F65<=79),AND($F65>=251,$F65<=400)),Metodo!$C$29,Metodo!$C$30)))+IFERROR(INDEX(Metodo!$C$32:$C$35,MATCH($G65,Metodo!$B$32:$B$35,0)),0)+COUNTIF($H65:$J65,"Sim")*Metodo!$C$37+IFERROR(INDEX(Metodo!$C$39:$C$41,MATCH($K65,Metodo!$B$39:$B$41,0)),0)) | M65: =IF($L65="","",IF($L65>=Metodo!$C$43,"A",IF($L65>=Metodo!$C$44,"B","C"))) | N65: Nao contatado | Q65: Primeiro contato | T65: Tier 3 (varredura TomTom 2026-08-29, PR #185). Qualificacao: site próprio.
A66: =IF($B66="","",ROW()-1) | B66: Crossfit Espaço Cerâmica | C66: São Caetano do Sul - São José | E66: +55 11 94453-0999 | K66: Grande SP | L66: =IF($B66="","",IF($F66="",Metodo!$C$30,IF(AND($F66>=80,$F66<=250),Metodo!$C$28,IF(OR(AND($F66>=40,$F66<=79),AND($F66>=251,$F66<=400)),Metodo!$C$29,Metodo!$C$30)))+IFERROR(INDEX(Metodo!$C$32:$C$35,MATCH($G66,Metodo!$B$32:$B$35,0)),0)+COUNTIF($H66:$J66,"Sim")*Metodo!$C$37+IFERROR(INDEX(Metodo!$C$39:$C$41,MATCH($K66,Metodo!$B$39:$B$41,0)),0)) | M66: =IF($L66="","",IF($L66>=Metodo!$C$43,"A",IF($L66>=Metodo!$C$44,"B","C"))) | N66: Nao contatado | Q66: Primeiro contato | T66: Tier 3 (varredura TomTom 2026-08-29, PR #185). Qualificacao: site próprio.
A67: =IF($B67="","",ROW()-1) | B67: Crossfit Visconde | C67: São Caetano do Sul - Oswaldo Cruz | E67: +55 11 95279-6110 | K67: Grande SP | L67: =IF($B67="","",IF($F67="",Metodo!$C$30,IF(AND($F67>=80,$F67<=250),Metodo!$C$28,IF(OR(AND($F67>=40,$F67<=79),AND($F67>=251,$F67<=400)),Metodo!$C$29,Metodo!$C$30)))+IFERROR(INDEX(Metodo!$C$32:$C$35,MATCH($G67,Metodo!$B$32:$B$35,0)),0)+COUNTIF($H67:$J67,"Sim")*Metodo!$C$37+IFERROR(INDEX(Metodo!$C$39:$C$41,MATCH($K67,Metodo!$B$39:$B$41,0)),0)) | M67: =IF($L67="","",IF($L67>=Metodo!$C$43,"A",IF($L67>=Metodo!$C$44,"B","C"))) | N67: Nao contatado | Q67: Primeiro contato | T67: Tier 3 (varredura TomTom 2026-08-29, PR #185). Qualificacao: site próprio.
A68: =IF($B68="","",ROW()-1) | B68: Triple CrossFit | C68: São Caetano do Sul - Santa Paula | E68: +55 11 91069-4634 | K68: Grande SP | L68: =IF($B68="","",IF($F68="",Metodo!$C$30,IF(AND($F68>=80,$F68<=250),Metodo!$C$28,IF(OR(AND($F68>=40,$F68<=79),AND($F68>=251,$F68<=400)),Metodo!$C$29,Metodo!$C$30)))+IFERROR(INDEX(Metodo!$C$32:$C$35,MATCH($G68,Metodo!$B$32:$B$35,0)),0)+COUNTIF($H68:$J68,"Sim")*Metodo!$C$37+IFERROR(INDEX(Metodo!$C$39:$C$41,MATCH($K68,Metodo!$B$39:$B$41,0)),0)) | M68: =IF($L68="","",IF($L68>=Metodo!$C$43,"A",IF($L68>=Metodo!$C$44,"B","C"))) | N68: Nao contatado | Q68: Primeiro contato | T68: Tier 3 (varredura TomTom 2026-08-29, PR #185). Qualificacao: site próprio.
A69: =IF($B69="","",ROW()-1) | B69: 3050 CrossFit | C69: São Paulo - Jardim Paulista | E69: +55 11 99272-0789 | K69: Grande SP | L69: =IF($B69="","",IF($F69="",Metodo!$C$30,IF(AND($F69>=80,$F69<=250),Metodo!$C$28,IF(OR(AND($F69>=40,$F69<=79),AND($F69>=251,$F69<=400)),Metodo!$C$29,Metodo!$C$30)))+IFERROR(INDEX(Metodo!$C$32:$C$35,MATCH($G69,Metodo!$B$32:$B$35,0)),0)+COUNTIF($H69:$J69,"Sim")*Metodo!$C$37+IFERROR(INDEX(Metodo!$C$39:$C$41,MATCH($K69,Metodo!$B$39:$B$41,0)),0)) | M69: =IF($L69="","",IF($L69>=Metodo!$C$43,"A",IF($L69>=Metodo!$C$44,"B","C"))) | N69: Nao contatado | Q69: Primeiro contato | T69: Tier 3 (varredura TomTom 2026-08-29, PR #185). Qualificacao: site próprio.
A70: =IF($B70="","",ROW()-1) | B70: Atrium CrossFit | C70: São Paulo - Vila Andrade | E70: +55 11 91689-9090 | K70: Grande SP | L70: =IF($B70="","",IF($F70="",Metodo!$C$30,IF(AND($F70>=80,$F70<=250),Metodo!$C$28,IF(OR(AND($F70>=40,$F70<=79),AND($F70>=251,$F70<=400)),Metodo!$C$29,Metodo!$C$30)))+IFERROR(INDEX(Metodo!$C$32:$C$35,MATCH($G70,Metodo!$B$32:$B$35,0)),0)+COUNTIF($H70:$J70,"Sim")*Metodo!$C$37+IFERROR(INDEX(Metodo!$C$39:$C$41,MATCH($K70,Metodo!$B$39:$B$41,0)),0)) | M70: =IF($L70="","",IF($L70>=Metodo!$C$43,"A",IF($L70>=Metodo!$C$44,"B","C"))) | N70: Nao contatado | Q70: Primeiro contato | T70: Tier 3 (varredura TomTom 2026-08-29, PR #185). Qualificacao: site próprio.
A71: =IF($B71="","",ROW()-1) | B71: Blindado CrossFit | C71: São Paulo - Santo Amaro | E71: +55 11 2533-2894 | K71: Grande SP | L71: =IF($B71="","",IF($F71="",Metodo!$C$30,IF(AND($F71>=80,$F71<=250),Metodo!$C$28,IF(OR(AND($F71>=40,$F71<=79),AND($F71>=251,$F71<=400)),Metodo!$C$29,Metodo!$C$30)))+IFERROR(INDEX(Metodo!$C$32:$C$35,MATCH($G71,Metodo!$B$32:$B$35,0)),0)+COUNTIF($H71:$J71,"Sim")*Metodo!$C$37+IFERROR(INDEX(Metodo!$C$39:$C$41,MATCH($K71,Metodo!$B$39:$B$41,0)),0)) | M71: =IF($L71="","",IF($L71>=Metodo!$C$43,"A",IF($L71>=Metodo!$C$44,"B","C"))) | N71: Nao contatado | Q71: Primeiro contato | T71: Tier 3 (varredura TomTom 2026-08-29, PR #185). Qualificacao: site próprio.
... A76: =IF($B76="","",ROW()-1) | B76: CrossFit Chácara | C76: São Paulo - Santo Amaro | E76: +55 11 3467-9077 | K76: Grande SP | L76: =IF($B76="","",IF($F76="",Metodo!$C$30,IF(AND($F76>=80,$F76<=250),Metodo!$C$28,IF(OR(AND($F76>=40,$F76<=79),AND($F76>=251,$F76<=400)),Metodo!$C$29,Metodo!$C$30)))+IFERROR(INDEX(Metodo!$C$32:$C$35,MATCH($G76,Metodo!$B$32:$B$35,0)),0)+COUNTIF($H76:$J76,"Sim")*Metodo!$C$37+IFERROR(INDEX(Metodo!$C$39:$C$41,MATCH($K76,Metodo!$B$39:$B$41,0)),0)) | M76: =IF($L76="","",IF($L76>=Metodo!$C$43,"A",IF($L76>=Metodo!$C$44,"B","C"))) | N76: Nao contatado | Q76: Primeiro contato | T76: Tier 3 (varredura TomTom 2026-08-29, PR #185). Qualificacao: site próprio.
A77: =IF($B77="","",ROW()-1) | B77: CrossFit Cobra | C77: São Paulo - Saúde | K77: Grande SP | L77: =IF($B77="","",IF($F77="",Metodo!$C$30,IF(AND($F77>=80,$F77<=250),Metodo!$C$28,IF(OR(AND($F77>=40,$F77<=79),AND($F77>=251,$F77<=400)),Metodo!$C$29,Metodo!$C$30)))+IFERROR(INDEX(Metodo!$C$32:$C$35,MATCH($G77,Metodo!$B$32:$B$35,0)),0)+COUNTIF($H77:$J77,"Sim")*Metodo!$C$37+IFERROR(INDEX(Metodo!$C$39:$C$41,MATCH($K77,Metodo!$B$39:$B$41,0)),0)) | M77: =IF($L77="","",IF($L77>=Metodo!$C$43,"A",IF($L77>=Metodo!$C$44,"B","C"))) | N77: Nao contatado | Q77: Achar contato | T77: Tier 3 (varredura TomTom 2026-08-29, PR #185). Qualificacao: sem site.
A78: =IF($B78="","",ROW()-1) | B78: CrossFit ERM | C78: São Paulo - Ermelino Matarazzo | E78: +55 11 94796-5748 | K78: Grande SP | L78: =IF($B78="","",IF($F78="",Metodo!$C$30,IF(AND($F78>=80,$F78<=250),Metodo!$C$28,IF(OR(AND($F78>=40,$F78<=79),AND($F78>=251,$F78<=400)),Metodo!$C$29,Metodo!$C$30)))+IFERROR(INDEX(Metodo!$C$32:$C$35,MATCH($G78,Metodo!$B$32:$B$35,0)),0)+COUNTIF($H78:$J78,"Sim")*Metodo!$C$37+IFERROR(INDEX(Metodo!$C$39:$C$41,MATCH($K78,Metodo!$B$39:$B$41,0)),0)) | M78: =IF($L78="","",IF($L78>=Metodo!$C$43,"A",IF($L78>=Metodo!$C$44,"B","C"))) | N78: Nao contatado | Q78: Primeiro contato | T78: Tier 3 (varredura TomTom 2026-08-29, PR #185). Qualificacao: site próprio.
A79: =IF($B79="","",ROW()-1) | B79: CrossFit Great Bear | C79: São Paulo - Sacomã | E79: +55 11 2307-3273 | K79: Grande SP | L79: =IF($B79="","",IF($F79="",Metodo!$C$30,IF(AND($F79>=80,$F79<=250),Metodo!$C$28,IF(OR(AND($F79>=40,$F79<=79),AND($F79>=251,$F79<=400)),Metodo!$C$29,Metodo!$C$30)))+IFERROR(INDEX(Metodo!$C$32:$C$35,MATCH($G79,Metodo!$B$32:$B$35,0)),0)+COUNTIF($H79:$J79,"Sim")*Metodo!$C$37+IFERROR(INDEX(Metodo!$C$39:$C$41,MATCH($K79,Metodo!$B$39:$B$41,0)),0)) | M79: =IF($L79="","",IF($L79>=Metodo!$C$43,"A",IF($L79>=Metodo!$C$44,"B","C"))) | N79: Nao contatado | Q79: Primeiro contato | T79: Tier 3 (varredura TomTom 2026-08-29, PR #185). Qualificacao: sem site.
A80: =IF($B80="","",ROW()-1) | B80: CrossFit Ipiranga | C80: São Paulo - Ipiranga | E80: +55 11 98329-6279 | K80: Grande SP | L80: =IF($B80="","",IF($F80="",Metodo!$C$30,IF(AND($F80>=80,$F80<=250),Metodo!$C$28,IF(OR(AND($F80>=40,$F80<=79),AND($F80>=251,$F80<=400)),Metodo!$C$29,Metodo!$C$30)))+IFERROR(INDEX(Metodo!$C$32:$C$35,MATCH($G80,Metodo!$B$32:$B$35,0)),0)+COUNTIF($H80:$J80,"Sim")*Metodo!$C$37+IFERROR(INDEX(Metodo!$C$39:$C$41,MATCH($K80,Metodo!$B$39:$B$41,0)),0)) | M80: =IF($L80="","",IF($L80>=Metodo!$C$43,"A",IF($L80>=Metodo!$C$44,"B","C"))) | N80: Nao contatado | Q80: Primeiro contato | T80: Tier 3 (varredura TomTom 2026-08-29, PR #185). Qualificacao: site próprio.
A81: =IF($B81="","",ROW()-1) | B81: CrossFit Ironhead | C81: São Paulo - Vila Andrade | E81: +55 11 97700-0085 | K81: Grande SP | L81: =IF($B81="","",IF($F81="",Metodo!$C$30,IF(AND($F81>=80,$F81<=250),Metodo!$C$28,IF(OR(AND($F81>=40,$F81<=79),AND($F81>=251,$F81<=400)),Metodo!$C$29,Metodo!$C$30)))+IFERROR(INDEX(Metodo!$C$32:$C$35,MATCH($G81,Metodo!$B$32:$B$35,0)),0)+COUNTIF($H81:$J81,"Sim")*Metodo!$C$37+IFERROR(INDEX(Metodo!$C$39:$C$41,MATCH($K81,Metodo!$B$39:$B$41,0)),0)) | M81: =IF($L81="","",IF($L81>=Metodo!$C$43,"A",IF($L81>=Metodo!$C$44,"B","C"))) | N81: Nao contatado | Q81: Primeiro contato | T81: Tier 3 (varredura TomTom 2026-08-29, PR #185). Qualificacao: site próprio.
A82: =IF($B82="","",ROW()-1) | B82: CrossFit Jaceru | C82: São Paulo - Itaim Bibi | K82: Grande SP | L82: =IF($B82="","",IF($F82="",Metodo!$C$30,IF(AND($F82>=80,$F82<=250),Metodo!$C$28,IF(OR(AND($F82>=40,$F82<=79),AND($F82>=251,$F82<=400)),Metodo!$C$29,Metodo!$C$30)))+IFERROR(INDEX(Metodo!$C$32:$C$35,MATCH($G82,Metodo!$B$32:$B$35,0)),0)+COUNTIF($H82:$J82,"Sim")*Metodo!$C$37+IFERROR(INDEX(Metodo!$C$39:$C$41,MATCH($K82,Metodo!$B$39:$B$41,0)),0)) | M82: =IF($L82="","",IF($L82>=Metodo!$C$43,"A",IF($L82>=Metodo!$C$44,"B","C"))) | N82: Nao contatado | Q82: Achar contato | T82: Tier 3 (varredura TomTom 2026-08-29, PR #185). Qualificacao: site próprio.
A83: =IF($B83="","",ROW()-1) | B83: CrossFit Lion Shield | C83: São Paulo - Vila Matilde | E83: +55 11 2653-5800 | K83: Grande SP | L83: =IF($B83="","",IF($F83="",Metodo!$C$30,IF(AND($F83>=80,$F83<=250),Metodo!$C$28,IF(OR(AND($F83>=40,$F83<=79),AND($F83>=251,$F83<=400)),Metodo!$C$29,Metodo!$C$30)))+IFERROR(INDEX(Metodo!$C$32:$C$35,MATCH($G83,Metodo!$B$32:$B$35,0)),0)+COUNTIF($H83:$J83,"Sim")*Metodo!$C$37+IFERROR(INDEX(Metodo!$C$39:$C$41,MATCH($K83,Metodo!$B$39:$B$41,0)),0)) | M83: =IF($L83="","",IF($L83>=Metodo!$C$43,"A",IF($L83>=Metodo!$C$44,"B","C"))) | N83: Nao contatado | Q83: Primeiro contato | T83: Tier 3 (varredura TomTom 2026-08-29, PR #185). Qualificacao: site próprio.
A84: =IF($B84="","",ROW()-1) | B84: CrossFit Mansion | C84: São Paulo - Perdizes | E84: +55 11 2364-2741 | K84: Grande SP | L84: =IF($B84="","",IF($F84="",Metodo!$C$30,IF(AND($F84>=80,$F84<=250),Metodo!$C$28,IF(OR(AND($F84>=40,$F84<=79),AND($F84>=251,$F84<=400)),Metodo!$C$29,Metodo!$C$30)))+IFERROR(INDEX(Metodo!$C$32:$C$35,MATCH($G84,Metodo!$B$32:$B$35,0)),0)+COUNTIF($H84:$J84,"Sim")*Metodo!$C$37+IFERROR(INDEX(Metodo!$C$39:$C$41,MATCH($K84,Metodo!$B$39:$B$41,0)),0)) | M84: =IF($L84="","",IF($L84>=Metodo!$C$43,"A",IF($L84>=Metodo!$C$44,"B","C"))) | N84: Nao contatado | Q84: Primeiro contato | T84: Tier 3 (varredura TomTom 2026-08-29, PR #185). Qualificacao: site próprio.
A85: =IF($B85="","",ROW()-1) | B85: CrossFit Moema | C85: São Paulo - Moema | E85: +55 11 99359-3910 | K85: Grande SP | L85: =IF($B85="","",IF($F85="",Metodo!$C$30,IF(AND($F85>=80,$F85<=250),Metodo!$C$28,IF(OR(AND($F85>=40,$F85<=79),AND($F85>=251,$F85<=400)),Metodo!$C$29,Metodo!$C$30)))+IFERROR(INDEX(Metodo!$C$32:$C$35,MATCH($G85,Metodo!$B$32:$B$35,0)),0)+COUNTIF($H85:$J85,"Sim")*Metodo!$C$37+IFERROR(INDEX(Metodo!$C$39:$C$41,MATCH($K85,Metodo!$B$39:$B$41,0)),0)) | M85: =IF($L85="","",IF($L85>=Metodo!$C$43,"A",IF($L85>=Metodo!$C$44,"B","C"))) | N85: Nao contatado | Q85: Primeiro contato | T85: Tier 3 (varredura TomTom 2026-08-29, PR #185). Qualificacao: site próprio.
A86: =IF($B86="","",ROW()-1) | B86: CrossFit Perdizes | C86: São Paulo - Perdizes | E86: +55 11 97050-4359 | K86: Grande SP | L86: =IF($B86="","",IF($F86="",Metodo!$C$30,IF(AND($F86>=80,$F86<=250),Metodo!$C$28,IF(OR(AND($F86>=40,$F86<=79),AND($F86>=251,$F86<=400)),Metodo!$C$29,Metodo!$C$30)))+IFERROR(INDEX(Metodo!$C$32:$C$35,MATCH($G86,Metodo!$B$32:$B$35,0)),0)+COUNTIF($H86:$J86,"Sim")*Metodo!$C$37+IFERROR(INDEX(Metodo!$C$39:$C$41,MATCH($K86,Metodo!$B$39:$B$41,0)),0)) | M86: =IF($L86="","",IF($L86>=Metodo!$C$43,"A",IF($L86>=Metodo!$C$44,"B","C"))) | N86: Nao contatado | Q86: Primeiro contato | T86: Tier 3 (varredura TomTom 2026-08-29, PR #185). Qualificacao: site próprio.
A87: =IF($B87="","",ROW()-1) | B87: CrossFit Pinheiros | C87: São Paulo - Pinheiros | E87: +55 11 98244-3068 | K87: Grande SP | L87: =IF($B87="","",IF($F87="",Metodo!$C$30,IF(AND($F87>=80,$F87<=250),Metodo!$C$28,IF(OR(AND($F87>=40,$F87<=79),AND($F87>=251,$F87<=400)),Metodo!$C$29,Metodo!$C$30)))+IFERROR(INDEX(Metodo!$C$32:$C$35,MATCH($G87,Metodo!$B$32:$B$35,0)),0)+COUNTIF($H87:$J87,"Sim")*Metodo!$C$37+IFERROR(INDEX(Metodo!$C$39:$C$41,MATCH($K87,Metodo!$B$39:$B$41,0)),0)) | M87: =IF($L87="","",IF($L87>=Metodo!$C$43,"A",IF($L87>=Metodo!$C$44,"B","C"))) | N87: Nao contatado | Q87: Primeiro contato | T87: Tier 3 (varredura TomTom 2026-08-29, PR #185). Qualificacao: site próprio.
A88: =IF($B88="","",ROW()-1) | B88: CrossFit SP | C88: São Paulo - Itaim Bibi | E88: +55 11 99229-6469 | K88: Grande SP | L88: =IF($B88="","",IF($F88="",Metodo!$C$30,IF(AND($F88>=80,$F88<=250),Metodo!$C$28,IF(OR(AND($F88>=40,$F88<=79),AND($F88>=251,$F88<=400)),Metodo!$C$29,Metodo!$C$30)))+IFERROR(INDEX(Metodo!$C$32:$C$35,MATCH($G88,Metodo!$B$32:$B$35,0)),0)+COUNTIF($H88:$J88,"Sim")*Metodo!$C$37+IFERROR(INDEX(Metodo!$C$39:$C$41,MATCH($K88,Metodo!$B$39:$B$41,0)),0)) | M88: =IF($L88="","",IF($L88>=Metodo!$C$43,"A",IF($L88>=Metodo!$C$44,"B","C"))) | N88: Nao contatado | Q88: Primeiro contato | T88: Tier 3 (varredura TomTom 2026-08-29, PR #185). Qualificacao: site próprio.
A89: =IF($B89="","",ROW()-1) | B89: CrossFit Santa Romana | C89: São Paulo - Pirituba | E89: +55 11 98915-9013 | K89: Grande SP | L89: =IF($B89="","",IF($F89="",Metodo!$C$30,IF(AND($F89>=80,$F89<=250),Metodo!$C$28,IF(OR(AND($F89>=40,$F89<=79),AND($F89>=251,$F89<=400)),Metodo!$C$29,Metodo!$C$30)))+IFERROR(INDEX(Metodo!$C$32:$C$35,MATCH($G89,Metodo!$B$32:$B$35,0)),0)+COUNTIF($H89:$J89,"Sim")*Metodo!$C$37+IFERROR(INDEX(Metodo!$C$39:$C$41,MATCH($K89,Metodo!$B$39:$B$41,0)),0)) | M89: =IF($L89="","",IF($L89>=Metodo!$C$43,"A",IF($L89>=Metodo!$C$44,"B","C"))) | N89: Nao contatado | Q89: Primeiro contato | T89: Tier 3 (varredura TomTom 2026-08-29, PR #185). Qualificacao: site próprio.
A90: =IF($B90="","",ROW()-1) | B90: CrossFit Saúde Anchieta | C90: São Paulo - Sacomã | E90: +55 11 94451-9790 | K90: Grande SP | L90: =IF($B90="","",IF($F90="",Metodo!$C$30,IF(AND($F90>=80,$F90<=250),Metodo!$C$28,IF(OR(AND($F90>=40,$F90<=79),AND($F90>=251,$F90<=400)),Metodo!$C$29,Metodo!$C$30)))+IFERROR(INDEX(Metodo!$C$32:$C$35,MATCH($G90,Metodo!$B$32:$B$35,0)),0)+COUNTIF($H90:$J90,"Sim")*Metodo!$C$37+IFERROR(INDEX(Metodo!$C$39:$C$41,MATCH($K90,Metodo!$B$39:$B$41,0)),0)) | M90: =IF($L90="","",IF($L90>=Metodo!$C$43,"A",IF($L90>=Metodo!$C$44,"B","C"))) | N90: Nao contatado | Q90: Primeiro contato | T90: Tier 3 (varredura TomTom 2026-08-29, PR #185). Qualificacao: site próprio.
A91: =IF($B91="","",ROW()-1) | B91: CrossFit Tatuapé | C91: São Paulo - Tatuapé | E91: +55 11 96260-1047 | K91: Grande SP | L91: =IF($B91="","",IF($F91="",Metodo!$C$30,IF(AND($F91>=80,$F91<=250),Metodo!$C$28,IF(OR(AND($F91>=40,$F91<=79),AND($F91>=251,$F91<=400)),Metodo!$C$29,Metodo!$C$30)))+IFERROR(INDEX(Metodo!$C$32:$C$35,MATCH($G91,Metodo!$B$32:$B$35,0)),0)+COUNTIF($H91:$J91,"Sim")*Metodo!$C$37+IFERROR(INDEX(Metodo!$C$39:$C$41,MATCH($K91,Metodo!$B$39:$B$41,0)),0)) | M91: =IF($L91="","",IF($L91>=Metodo!$C$43,"A",IF($L91>=Metodo!$C$44,"B","C"))) | N91: Nao contatado | Q91: Primeiro contato | T91: Tier 3 (varredura TomTom 2026-08-29, PR #185). Qualificacao: site próprio.
A92: =IF($B92="","",ROW()-1) | B92: CrossFit Teina | C92: São Paulo - Ipiranga | E92: +55 11 99887-1523 | K92: Grande SP | L92: =IF($B92="","",IF($F92="",Metodo!$C$30,IF(AND($F92>=80,$F92<=250),Metodo!$C$28,IF(OR(AND($F92>=40,$F92<=79),AND($F92>=251,$F92<=400)),Metodo!$C$29,Metodo!$C$30)))+IFERROR(INDEX(Metodo!$C$32:$C$35,MATCH($G92,Metodo!$B$32:$B$35,0)),0)+COUNTIF($H92:$J92,"Sim")*Metodo!$C$37+IFERROR(INDEX(Metodo!$C$39:$C$41,MATCH($K92,Metodo!$B$39:$B$41,0)),0)) | M92: =IF($L92="","",IF($L92>=Metodo!$C$43,"A",IF($L92>=Metodo!$C$44,"B","C"))) | N92: Nao contatado | Q92: Primeiro contato | T92: Tier 3 (varredura TomTom 2026-08-29, PR #185). Qualificacao: site próprio.
A93: =IF($B93="","",ROW()-1) | B93: CrossFit Volk | C93: São Paulo - Vila Mariana | E93: +55 11 2619-1038 | K93: Grande SP | L93: =IF($B93="","",IF($F93="",Metodo!$C$30,IF(AND($F93>=80,$F93<=250),Metodo!$C$28,IF(OR(AND($F93>=40,$F93<=79),AND($F93>=251,$F93<=400)),Metodo!$C$29,Metodo!$C$30)))+IFERROR(INDEX(Metodo!$C$32:$C$35,MATCH($G93,Metodo!$B$32:$B$35,0)),0)+COUNTIF($H93:$J93,"Sim")*Metodo!$C$37+IFERROR(INDEX(Metodo!$C$39:$C$41,MATCH($K93,Metodo!$B$39:$B$41,0)),0)) | M93: =IF($L93="","",IF($L93>=Metodo!$C$43,"A",IF($L93>=Metodo!$C$44,"B","C"))) | N93: Nao contatado | Q93: Primeiro contato | T93: Tier 3 (varredura TomTom 2026-08-29, PR #185). Qualificacao: site próprio.
A94: =IF($B94="","",ROW()-1) | B94: CrossFit ZN 2 | C94: São Paulo - Tucuruvi | D94: @ct_zn_ | E94: +55 11 99906-2601 | K94: Grande SP | L94: =IF($B94="","",IF($F94="",Metodo!$C$30,IF(AND($F94>=80,$F94<=250),Metodo!$C$28,IF(OR(AND($F94>=40,$F94<=79),AND($F94>=251,$F94<=400)),Metodo!$C$29,Metodo!$C$30)))+IFERROR(INDEX(Metodo!$C$32:$C$35,MATCH($G94,Metodo!$B$32:$B$35,0)),0)+COUNTIF($H94:$J94,"Sim")*Metodo!$C$37+IFERROR(INDEX(Metodo!$C$39:$C$41,MATCH($K94,Metodo!$B$39:$B$41,0)),0)) | M94: =IF($L94="","",IF($L94>=Metodo!$C$43,"A",IF($L94>=Metodo!$C$44,"B","C"))) | N94: Nao contatado | Q94: Primeiro contato | T94: Tier 3 (varredura TomTom 2026-08-29, PR #185). Qualificacao: site proprio. Instagram @ct_zn_, Tucuruvi. Box competitivo - participa de Open e challenges internos. Cuidado: existe outro lead "Crossfit Zn" (linha 113, Santana) com nome parecido mas telefone diferente - nao confundir na abordagem.
A95: =IF($B95="","",ROW()-1) | B95: Crossfit 79 | C95: São Paulo - Pinheiros | E95: +55 11 3853-5042 | K95: Grande SP | L95: =IF($B95="","",IF($F95="",Metodo!$C$30,IF(AND($F95>=80,$F95<=250),Metodo!$C$28,IF(OR(AND($F95>=40,$F95<=79),AND($F95>=251,$F95<=400)),Metodo!$C$29,Metodo!$C$30)))+IFERROR(INDEX(Metodo!$C$32:$C$35,MATCH($G95,Metodo!$B$32:$B$35,0)),0)+COUNTIF($H95:$J95,"Sim")*Metodo!$C$37+IFERROR(INDEX(Metodo!$C$39:$C$41,MATCH($K95,Metodo!$B$39:$B$41,0)),0)) | M95: =IF($L95="","",IF($L95>=Metodo!$C$43,"A",IF($L95>=Metodo!$C$44,"B","C"))) | N95: Nao contatado | Q95: Primeiro contato | T95: Tier 3 (varredura TomTom 2026-08-29, PR #185). Qualificacao: site próprio.
A96: =IF($B96="","",ROW()-1) | B96: Crossfit Academia para Mulheres | C96: São Paulo - Sapopemba | E96: +55 14 99153-0682 | K96: Grande SP | L96: =IF($B96="","",IF($F96="",Metodo!$C$30,IF(AND($F96>=80,$F96<=250),Metodo!$C$28,IF(OR(AND($F96>=40,$F96<=79),AND($F96>=251,$F96<=400)),Metodo!$C$29,Metodo!$C$30)))+IFERROR(INDEX(Metodo!$C$32:$C$35,MATCH($G96,Metodo!$B$32:$B$35,0)),0)+COUNTIF($H96:$J96,"Sim")*Metodo!$C$37+IFERROR(INDEX(Metodo!$C$39:$C$41,MATCH($K96,Metodo!$B$39:$B$41,0)),0)) | M96: =IF($L96="","",IF($L96>=Metodo!$C$43,"A",IF($L96>=Metodo!$C$44,"B","C"))) | N96: Nao contatado | Q96: Primeiro contato | T96: Tier 3 (varredura TomTom 2026-08-29, PR #185). Qualificacao: sem site.
A97: =IF($B97="","",ROW()-1) | B97: Crossfit Bizarro | C97: São Paulo - Mandaqui | K97: Grande SP | L97: =IF($B97="","",IF($F97="",Metodo!$C$30,IF(AND($F97>=80,$F97<=250),Metodo!$C$28,IF(OR(AND($F97>=40,$F97<=79),AND($F97>=251,$F97<=400)),Metodo!$C$29,Metodo!$C$30)))+IFERROR(INDEX(Metodo!$C$32:$C$35,MATCH($G97,Metodo!$B$32:$B$35,0)),0)+COUNTIF($H97:$J97,"Sim")*Metodo!$C$37+IFERROR(INDEX(Metodo!$C$39:$C$41,MATCH($K97,Metodo!$B$39:$B$41,0)),0)) | M97: =IF($L97="","",IF($L97>=Metodo!$C$43,"A",IF($L97>=Metodo!$C$44,"B","C"))) | N97: Nao contatado | Q97: Achar contato | T97: Tier 3 (varredura TomTom 2026-08-29, PR #185). Qualificacao: sem site.
A98: =IF($B98="","",ROW()-1) | B98: Crossfit Caveira | C98: São Paulo - Butantã | E98: +55 11 3213-4611 | K98: Grande SP | L98: =IF($B98="","",IF($F98="",Metodo!$C$30,IF(AND($F98>=80,$F98<=250),Metodo!$C$28,IF(OR(AND($F98>=40,$F98<=79),AND($F98>=251,$F98<=400)),Metodo!$C$29,Metodo!$C$30)))+IFERROR(INDEX(Metodo!$C$32:$C$35,MATCH($G98,Metodo!$B$32:$B$35,0)),0)+COUNTIF($H98:$J98,"Sim")*Metodo!$C$37+IFERROR(INDEX(Metodo!$C$39:$C$41,MATCH($K98,Metodo!$B$39:$B$41,0)),0)) | M98: =IF($L98="","",IF($L98>=Metodo!$C$43,"A",IF($L98>=Metodo!$C$44,"B","C"))) | N98: Nao contatado | Q98: Primeiro contato | T98: Tier 3 (varredura TomTom 2026-08-29, PR #185). Qualificacao: site próprio.
A99: =IF($B99="","",ROW()-1) | B99: Crossfit Ki | C99: São Paulo - Vila Mariana | E99: +55 11 96574-6947 | K99: Grande SP | L99: =IF($B99="","",IF($F99="",Metodo!$C$30,IF(AND($F99>=80,$F99<=250),Metodo!$C$28,IF(OR(AND($F99>=40,$F99<=79),AND($F99>=251,$F99<=400)),Metodo!$C$29,Metodo!$C$30)))+IFERROR(INDEX(Metodo!$C$32:$C$35,MATCH($G99,Metodo!$B$32:$B$35,0)),0)+COUNTIF($H99:$J99,"Sim")*Metodo!$C$37+IFERROR(INDEX(Metodo!$C$39:$C$41,MATCH($K99,Metodo!$B$39:$B$41,0)),0)) | M99: =IF($L99="","",IF($L99>=Metodo!$C$43,"A",IF($L99>=Metodo!$C$44,"B","C"))) | N99: Nao contatado | Q99: Primeiro contato | T99: Tier 3 (varredura TomTom 2026-08-29, PR #185). Qualificacao: site próprio.
A100: =IF($B100="","",ROW()-1) | B100: Crossfit Mazzei | C100: São Paulo - Tremembe | K100: Grande SP | L100: =IF($B100="","",IF($F100="",Metodo!$C$30,IF(AND($F100>=80,$F100<=250),Metodo!$C$28,IF(OR(AND($F100>=40,$F100<=79),AND($F100>=251,$F100<=400)),Metodo!$C$29,Metodo!$C$30)))+IFERROR(INDEX(Metodo!$C$32:$C$35,MATCH($G100,Metodo!$B$32:$B$35,0)),0)+COUNTIF($H100:$J100,"Sim")*Metodo!$C$37+IFERROR(INDEX(Metodo!$C$39:$C$41,MATCH($K100,Metodo!$B$39:$B$41,0)),0)) | M100: =IF($L100="","",IF($L100>=Metodo!$C$43,"A",IF($L100>=Metodo!$C$44,"B","C"))) | N100: Nao contatado | Q100: Achar contato | T100: Tier 3 (varredura TomTom 2026-08-29, PR #185). Qualificacao: sem site.
A101: =IF($B101="","",ROW()-1) | B101: Crossfit Mister | C101: São Paulo - Vila Formosa | E101: +55 11 91089-2010 | K101: Grande SP | L101: =IF($B101="","",IF($F101="",Metodo!$C$30,IF(AND($F101>=80,$F101<=250),Metodo!$C$28,IF(OR(AND($F101>=40,$F101<=79),AND($F101>=251,$F101<=400)),Metodo!$C$29,Metodo!$C$30)))+IFERROR(INDEX(Metodo!$C$32:$C$35,MATCH($G101,Metodo!$B$32:$B$35,0)),0)+COUNTIF($H101:$J101,"Sim")*Metodo!$C$37+IFERROR(INDEX(Metodo!$C$39:$C$41,MATCH($K101,Metodo!$B$39:$B$41,0)),0)) | M101: =IF($L101="","",IF($L101>=Metodo!$C$43,"A",IF($L101>=Metodo!$C$44,"B","C"))) | N101: Nao contatado | Q101: Primeiro contato | T101: Tier 3 (varredura TomTom 2026-08-29, PR #185). Qualificacao: site próprio.
A102: =IF($B102="","",ROW()-1) | B102: Crossfit Mitra | C102: São Paulo - Campo Belo | E102: +55 11 98781-8553 | K102: Grande SP | L102: =IF($B102="","",IF($F102="",Metodo!$C$30,IF(AND($F102>=80,$F102<=250),Metodo!$C$28,IF(OR(AND($F102>=40,$F102<=79),AND($F102>=251,$F102<=400)),Metodo!$C$29,Metodo!$C$30)))+IFERROR(INDEX(Metodo!$C$32:$C$35,MATCH($G102,Metodo!$B$32:$B$35,0)),0)+COUNTIF($H102:$J102,"Sim")*Metodo!$C$37+IFERROR(INDEX(Metodo!$C$39:$C$41,MATCH($K102,Metodo!$B$39:$B$41,0)),0)) | M102: =IF($L102="","",IF($L102>=Metodo!$C$43,"A",IF($L102>=Metodo!$C$44,"B","C"))) | N102: Nao contatado | Q102: Primeiro contato | T102: Tier 3 (varredura TomTom 2026-08-29, PR #185). Qualificacao: site próprio.
A103: =IF($B103="","",ROW()-1) | B103: Crossfit Norte | C103: São Paulo - Mandaqui | K103: Grande SP | L103: =IF($B103="","",IF($F103="",Metodo!$C$30,IF(AND($F103>=80,$F103<=250),Metodo!$C$28,IF(OR(AND($F103>=40,$F103<=79),AND($F103>=251,$F103<=400)),Metodo!$C$29,Metodo!$C$30)))+IFERROR(INDEX(Metodo!$C$32:$C$35,MATCH($G103,Metodo!$B$32:$B$35,0)),0)+COUNTIF($H103:$J103,"Sim")*Metodo!$C$37+IFERROR(INDEX(Metodo!$C$39:$C$41,MATCH($K103,Metodo!$B$39:$B$41,0)),0)) | M103: =IF($L103="","",IF($L103>=Metodo!$C$43,"A",IF($L103>=Metodo!$C$44,"B","C"))) | N103: Nao contatado | Q103: Achar contato | T103: Tier 3 (varredura TomTom 2026-08-29, PR #185). Qualificacao: sem site.
A104: =IF($B104="","",ROW()-1) | B104: Crossfit Revolut!on | C104: São Paulo - Belém | E104: +55 11 4741-2986 | K104: Grande SP | L104: =IF($B104="","",IF($F104="",Metodo!$C$30,IF(AND($F104>=80,$F104<=250),Metodo!$C$28,IF(OR(AND($F104>=40,$F104<=79),AND($F104>=251,$F104<=400)),Metodo!$C$29,Metodo!$C$30)))+IFERROR(INDEX(Metodo!$C$32:$C$35,MATCH($G104,Metodo!$B$32:$B$35,0)),0)+COUNTIF($H104:$J104,"Sim")*Metodo!$C$37+IFERROR(INDEX(Metodo!$C$39:$C$41,MATCH($K104,Metodo!$B$39:$B$41,0)),0)) | M104: =IF($L104="","",IF($L104>=Metodo!$C$43,"A",IF($L104>=Metodo!$C$44,"B","C"))) | N104: Nao contatado | Q104: Primeiro contato | T104: Tier 3 (varredura TomTom 2026-08-29, PR #185). Qualificacao: sem site.
A105: =IF($B105="","",ROW()-1) | B105: Crossfit Saúde | C105: São Paulo - Butantã | K105: Grande SP | L105: =IF($B105="","",IF($F105="",Metodo!$C$30,IF(AND($F105>=80,$F105<=250),Metodo!$C$28,IF(OR(AND($F105>=40,$F105<=79),AND($F105>=251,$F105<=400)),Metodo!$C$29,Metodo!$C$30)))+IFERROR(INDEX(Metodo!$C$32:$C$35,MATCH($G105,Metodo!$B$32:$B$35,0)),0)+COUNTIF($H105:$J105,"Sim")*Metodo!$C$37+IFERROR(INDEX(Metodo!$C$39:$C$41,MATCH($K105,Metodo!$B$39:$B$41,0)),0)) | M105: =IF($L105="","",IF($L105>=Metodo!$C$43,"A",IF($L105>=Metodo!$C$44,"B","C"))) | N105: Nao contatado | Q105: Achar contato | T105: Tier 3 (varredura TomTom 2026-08-29, PR #185). Qualificacao: site próprio.
A106: =IF($B106="","",ROW()-1) | B106: Crossfit Scorpios | C106: São Paulo - Ipiranga | E106: +55 11 2645-2444 | K106: Grande SP | L106: =IF($B106="","",IF($F106="",Metodo!$C$30,IF(AND($F106>=80,$F106<=250),Metodo!$C$28,IF(OR(AND($F106>=40,$F106<=79),AND($F106>=251,$F106<=400)),Metodo!$C$29,Metodo!$C$30)))+IFERROR(INDEX(Metodo!$C$32:$C$35,MATCH($G106,Metodo!$B$32:$B$35,0)),0)+COUNTIF($H106:$J106,"Sim")*Metodo!$C$37+IFERROR(INDEX(Metodo!$C$39:$C$41,MATCH($K106,Metodo!$B$39:$B$41,0)),0)) | M106: =IF($L106="","",IF($L106>=Metodo!$C$43,"A",IF($L106>=Metodo!$C$44,"B","C"))) | N106: Nao contatado | Q106: Primeiro contato | T106: Tier 3 (varredura TomTom 2026-08-29, PR #185). Qualificacao: sem site.
A107: =IF($B107="","",ROW()-1) | B107: Crossfit Seleção | C107: São Paulo - Santo Amaro | K107: Grande SP | L107: =IF($B107="","",IF($F107="",Metodo!$C$30,IF(AND($F107>=80,$F107<=250),Metodo!$C$28,IF(OR(AND($F107>=40,$F107<=79),AND($F107>=251,$F107<=400)),Metodo!$C$29,Metodo!$C$30)))+IFERROR(INDEX(Metodo!$C$32:$C$35,MATCH($G107,Metodo!$B$32:$B$35,0)),0)+COUNTIF($H107:$J107,"Sim")*Metodo!$C$37+IFERROR(INDEX(Metodo!$C$39:$C$41,MATCH($K107,Metodo!$B$39:$B$41,0)),0)) | M107: =IF($L107="","",IF($L107>=Metodo!$C$43,"A",IF($L107>=Metodo!$C$44,"B","C"))) | N107: Nao contatado | Q107: Achar contato | T107: Tier 3 (varredura TomTom 2026-08-29, PR #185). Qualificacao: sem site.
A108: =IF($B108="","",ROW()-1) | B108: Crossfit Sergipe | C108: São Paulo - Consolação | E108: +55 11 2679-2758 | K108: Grande SP | L108: =IF($B108="","",IF($F108="",Metodo!$C$30,IF(AND($F108>=80,$F108<=250),Metodo!$C$28,IF(OR(AND($F108>=40,$F108<=79),AND($F108>=251,$F108<=400)),Metodo!$C$29,Metodo!$C$30)))+IFERROR(INDEX(Metodo!$C$32:$C$35,MATCH($G108,Metodo!$B$32:$B$35,0)),0)+COUNTIF($H108:$J108,"Sim")*Metodo!$C$37+IFERROR(INDEX(Metodo!$C$39:$C$41,MATCH($K108,Metodo!$B$39:$B$41,0)),0)) | M108: =IF($L108="","",IF($L108>=Metodo!$C$43,"A",IF($L108>=Metodo!$C$44,"B","C"))) | N108: Nao contatado | Q108: Primeiro contato | T108: Tier 3 (varredura TomTom 2026-08-29, PR #185). Qualificacao: site próprio.
A109: =IF($B109="","",ROW()-1) | B109: Crossfit Simio | C109: São Paulo - Ipiranga | E109: +55 11 94519-3173 | K109: Grande SP | L109: =IF($B109="","",IF($F109="",Metodo!$C$30,IF(AND($F109>=80,$F109<=250),Metodo!$C$28,IF(OR(AND($F109>=40,$F109<=79),AND($F109>=251,$F109<=400)),Metodo!$C$29,Metodo!$C$30)))+IFERROR(INDEX(Metodo!$C$32:$C$35,MATCH($G109,Metodo!$B$32:$B$35,0)),0)+COUNTIF($H109:$J109,"Sim")*Metodo!$C$37+IFERROR(INDEX(Metodo!$C$39:$C$41,MATCH($K109,Metodo!$B$39:$B$41,0)),0)) | M109: =IF($L109="","",IF($L109>=Metodo!$C$43,"A",IF($L109>=Metodo!$C$44,"B","C"))) | N109: Nao contatado | Q109: Primeiro contato | T109: Tier 3 (varredura TomTom 2026-08-29, PR #185). Qualificacao: site próprio.
A110: =IF($B110="","",ROW()-1) | B110: Crossfit São Lucas | C110: São Paulo - São Lucas | E110: +55 11 2877-1377 | K110: Grande SP | L110: =IF($B110="","",IF($F110="",Metodo!$C$30,IF(AND($F110>=80,$F110<=250),Metodo!$C$28,IF(OR(AND($F110>=40,$F110<=79),AND($F110>=251,$F110<=400)),Metodo!$C$29,Metodo!$C$30)))+IFERROR(INDEX(Metodo!$C$32:$C$35,MATCH($G110,Metodo!$B$32:$B$35,0)),0)+COUNTIF($H110:$J110,"Sim")*Metodo!$C$37+IFERROR(INDEX(Metodo!$C$39:$C$41,MATCH($K110,Metodo!$B$39:$B$41,0)),0)) | M110: =IF($L110="","",IF($L110>=Metodo!$C$43,"A",IF($L110>=Metodo!$C$44,"B","C"))) | N110: Nao contatado | Q110: Primeiro contato | T110: Tier 3 (varredura TomTom 2026-08-29, PR #185). Qualificacao: site próprio.
A111: =IF($B111="","",ROW()-1) | B111: Crossfit Tucuruvi | C111: São Paulo - Tucuruvi | E111: +55 11 99845-4445 | K111: Grande SP | L111: =IF($B111="","",IF($F111="",Metodo!$C$30,IF(AND($F111>=80,$F111<=250),Metodo!$C$28,IF(OR(AND($F111>=40,$F111<=79),AND($F111>=251,$F111<=400)),Metodo!$C$29,Metodo!$C$30)))+IFERROR(INDEX(Metodo!$C$32:$C$35,MATCH($G111,Metodo!$B$32:$B$35,0)),0)+COUNTIF($H111:$J111,"Sim")*Metodo!$C$37+IFERROR(INDEX(Metodo!$C$39:$C$41,MATCH($K111,Metodo!$B$39:$B$41,0)),0)) | M111: =IF($L111="","",IF($L111>=Metodo!$C$43,"A",IF($L111>=Metodo!$C$44,"B","C"))) | N111: Nao contatado | Q111: Primeiro contato | T111: Tier 3 (varredura TomTom 2026-08-29, PR #185). Qualificacao: sem site. Instagram pequeno (21 posts), box novo/recente. Faz promocao tipo Black Friday - sinal de sensibilidade a preco e possivel dor de cobranca manual em campanha.
A112: =IF($B112="","",ROW()-1) | B112: Crossfit Zl | C112: São Paulo - Penha | E112: +55 11 98076-1578 | K112: Grande SP | L112: =IF($B112="","",IF($F112="",Metodo!$C$30,IF(AND($F112>=80,$F112<=250),Metodo!$C$28,IF(OR(AND($F112>=40,$F112<=79),AND($F112>=251,$F112<=400)),Metodo!$C$29,Metodo!$C$30)))+IFERROR(INDEX(Metodo!$C$32:$C$35,MATCH($G112,Metodo!$B$32:$B$35,0)),0)+COUNTIF($H112:$J112,"Sim")*Metodo!$C$37+IFERROR(INDEX(Metodo!$C$39:$C$41,MATCH($K112,Metodo!$B$39:$B$41,0)),0)) | M112: =IF($L112="","",IF($L112>=Metodo!$C$43,"A",IF($L112>=Metodo!$C$44,"B","C"))) | N112: Nao contatado | Q112: Primeiro contato | T112: Tier 3 (varredura TomTom 2026-08-29, PR #185). Qualificacao: site próprio.
A113: =IF($B113="","",ROW()-1) | B113: Crossfit Zn | C113: São Paulo - Santana | E113: +55 11 3567-4884 | K113: Grande SP | L113: =IF($B113="","",IF($F113="",Metodo!$C$30,IF(AND($F113>=80,$F113<=250),Metodo!$C$28,IF(OR(AND($F113>=40,$F113<=79),AND($F113>=251,$F113<=400)),Metodo!$C$29,Metodo!$C$30)))+IFERROR(INDEX(Metodo!$C$32:$C$35,MATCH($G113,Metodo!$B$32:$B$35,0)),0)+COUNTIF($H113:$J113,"Sim")*Metodo!$C$37+IFERROR(INDEX(Metodo!$C$39:$C$41,MATCH($K113,Metodo!$B$39:$B$41,0)),0)) | M113: =IF($L113="","",IF($L113>=Metodo!$C$43,"A",IF($L113>=Metodo!$C$44,"B","C"))) | N113: Nao contatado | Q113: Primeiro contato | T113: Tier 3 (varredura TomTom 2026-08-29, PR #185). Qualificacao: sem site. Santana, zona norte. Sinal fraco na busca (nome comum, resultados ambiguos com outros "CrossFit ZN") - abertura generica por bairro, nao usar detalhe de outro box por engano.
A114: =IF($B114="","",ROW()-1) | B114: Dobermann Crossfit | C114: São Paulo - Moema | E114: +55 11 99795-4171 | K114: Grande SP | L114: =IF($B114="","",IF($F114="",Metodo!$C$30,IF(AND($F114>=80,$F114<=250),Metodo!$C$28,IF(OR(AND($F114>=40,$F114<=79),AND($F114>=251,$F114<=400)),Metodo!$C$29,Metodo!$C$30)))+IFERROR(INDEX(Metodo!$C$32:$C$35,MATCH($G114,Metodo!$B$32:$B$35,0)),0)+COUNTIF($H114:$J114,"Sim")*Metodo!$C$37+IFERROR(INDEX(Metodo!$C$39:$C$41,MATCH($K114,Metodo!$B$39:$B$41,0)),0)) | M114: =IF($L114="","",IF($L114>=Metodo!$C$43,"A",IF($L114>=Metodo!$C$44,"B","C"))) | N114: Nao contatado | Q114: Primeiro contato | T114: Tier 3 (varredura TomTom 2026-08-29, PR #185). Qualificacao: site próprio.
A115: =IF($B115="","",ROW()-1) | B115: Flexus Crossfit | C115: São Paulo - Santana | K115: Grande SP | L115: =IF($B115="","",IF($F115="",Metodo!$C$30,IF(AND($F115>=80,$F115<=250),Metodo!$C$28,IF(OR(AND($F115>=40,$F115<=79),AND($F115>=251,$F115<=400)),Metodo!$C$29,Metodo!$C$30)))+IFERROR(INDEX(Metodo!$C$32:$C$35,MATCH($G115,Metodo!$B$32:$B$35,0)),0)+COUNTIF($H115:$J115,"Sim")*Metodo!$C$37+IFERROR(INDEX(Metodo!$C$39:$C$41,MATCH($K115,Metodo!$B$39:$B$41,0)),0)) | M115: =IF($L115="","",IF($L115>=Metodo!$C$43,"A",IF($L115>=Metodo!$C$44,"B","C"))) | N115: Nao contatado | Q115: Achar contato | T115: Tier 3 (varredura TomTom 2026-08-29, PR #185). Qualificacao: sem site.
A116: =IF($B116="","",ROW()-1) | B116: Hangar 193 Crossfit | C116: São Paulo - Vila Leopoldina | E116: +55 11 3473-8400 | K116: Grande SP | L116: =IF($B116="","",IF($F116="",Metodo!$C$30,IF(AND($F116>=80,$F116<=250),Metodo!$C$28,IF(OR(AND($F116>=40,$F116<=79),AND($F116>=251,$F116<=400)),Metodo!$C$29,Metodo!$C$30)))+IFERROR(INDEX(Metodo!$C$32:$C$35,MATCH($G116,Metodo!$B$32:$B$35,0)),0)+COUNTIF($H116:$J116,"Sim")*Metodo!$C$37+IFERROR(INDEX(Metodo!$C$39:$C$41,MATCH($K116,Metodo!$B$39:$B$41,0)),0)) | M116: =IF($L116="","",IF($L116>=Metodo!$C$43,"A",IF($L116>=Metodo!$C$44,"B","C"))) | N116: Nao contatado | Q116: Primeiro contato | T116: Tier 3 (varredura TomTom 2026-08-29, PR #185). Qualificacao: site próprio.
A117: =IF($B117="","",ROW()-1) | B117: Irmãos Crossfit | C117: São Paulo - Lapa | E117: +55 11 4117-1921 | K117: Grande SP | L117: =IF($B117="","",IF($F117="",Metodo!$C$30,IF(AND($F117>=80,$F117<=250),Metodo!$C$28,IF(OR(AND($F117>=40,$F117<=79),AND($F117>=251,$F117<=400)),Metodo!$C$29,Metodo!$C$30)))+IFERROR(INDEX(Metodo!$C$32:$C$35,MATCH($G117,Metodo!$B$32:$B$35,0)),0)+COUNTIF($H117:$J117,"Sim")*Metodo!$C$37+IFERROR(INDEX(Metodo!$C$39:$C$41,MATCH($K117,Metodo!$B$39:$B$41,0)),0)) | M117: =IF($L117="","",IF($L117>=Metodo!$C$43,"A",IF($L117>=Metodo!$C$44,"B","C"))) | N117: Nao contatado | Q117: Primeiro contato | T117: Tier 3 (varredura TomTom 2026-08-29, PR #185). Qualificacao: site próprio.
A118: =IF($B118="","",ROW()-1) | B118: Kampu CrossFit | C118: São Paulo - Itaim Bibi | E118: +55 11 5041-4338 | K118: Grande SP | L118: =IF($B118="","",IF($F118="",Metodo!$C$30,IF(AND($F118>=80,$F118<=250),Metodo!$C$28,IF(OR(AND($F118>=40,$F118<=79),AND($F118>=251,$F118<=400)),Metodo!$C$29,Metodo!$C$30)))+IFERROR(INDEX(Metodo!$C$32:$C$35,MATCH($G118,Metodo!$B$32:$B$35,0)),0)+COUNTIF($H118:$J118,"Sim")*Metodo!$C$37+IFERROR(INDEX(Metodo!$C$39:$C$41,MATCH($K118,Metodo!$B$39:$B$41,0)),0)) | M118: =IF($L118="","",IF($L118>=Metodo!$C$43,"A",IF($L118>=Metodo!$C$44,"B","C"))) | N118: Nao contatado | Q118: Primeiro contato | T118: Tier 3 (varredura TomTom 2026-08-29, PR #185). Qualificacao: site próprio.
A119: =IF($B119="","",ROW()-1) | B119: Muralha CrossFit | C119: São Paulo - Saúde | E119: +55 11 2384-2878 | K119: Grande SP | L119: =IF($B119="","",IF($F119="",Metodo!$C$30,IF(AND($F119>=80,$F119<=250),Metodo!$C$28,IF(OR(AND($F119>=40,$F119<=79),AND($F119>=251,$F119<=400)),Metodo!$C$29,Metodo!$C$30)))+IFERROR(INDEX(Metodo!$C$32:$C$35,MATCH($G119,Metodo!$B$32:$B$35,0)),0)+COUNTIF($H119:$J119,"Sim")*Metodo!$C$37+IFERROR(INDEX(Metodo!$C$39:$C$41,MATCH($K119,Metodo!$B$39:$B$41,0)),0)) | M119: =IF($L119="","",IF($L119>=Metodo!$C$43,"A",IF($L119>=Metodo!$C$44,"B","C"))) | N119: Nao contatado | Q119: Primeiro contato | T119: Tier 3 (varredura TomTom 2026-08-29, PR #185). Qualificacao: site próprio.
A120: =IF($B120="","",ROW()-1) | B120: Studio Funcional & Crossfit | C120: São Paulo - Tucuruvi | E120: +55 11 99276-5033 | K120: Grande SP | L120: =IF($B120="","",IF($F120="",Metodo!$C$30,IF(AND($F120>=80,$F120<=250),Metodo!$C$28,IF(OR(AND($F120>=40,$F120<=79),AND($F120>=251,$F120<=400)),Metodo!$C$29,Metodo!$C$30)))+IFERROR(INDEX(Metodo!$C$32:$C$35,MATCH($G120,Metodo!$B$32:$B$35,0)),0)+COUNTIF($H120:$J120,"Sim")*Metodo!$C$37+IFERROR(INDEX(Metodo!$C$39:$C$41,MATCH($K120,Metodo!$B$39:$B$41,0)),0)) | M120: =IF($L120="","",IF($L120>=Metodo!$C$43,"A",IF($L120>=Metodo!$C$44,"B","C"))) | N120: Nao contatado | Q120: Primeiro contato | T120: Tier 3 (varredura TomTom 2026-08-29, PR #185). Qualificacao: site proprio. Tucuruvi. Sinal fraco na busca - mas o proprio nome ja diz que atende funcional + crossfit, publico mais amplo que um box crossfit puro.
A121: =IF($B121="","",ROW()-1) | B121: Vigor Crossfit | C121: São Paulo - Jaguaré | K121: Grande SP | L121: =IF($B121="","",IF($F121="",Metodo!$C$30,IF(AND($F121>=80,$F121<=250),Metodo!$C$28,IF(OR(AND($F121>=40,$F121<=79),AND($F121>=251,$F121<=400)),Metodo!$C$29,Metodo!$C$30)))+IFERROR(INDEX(Metodo!$C$32:$C$35,MATCH($G121,Metodo!$B$32:$B$35,0)),0)+COUNTIF($H121:$J121,"Sim")*Metodo!$C$37+IFERROR(INDEX(Metodo!$C$39:$C$41,MATCH($K121,Metodo!$B$39:$B$41,0)),0)) | M121: =IF($L121="","",IF($L121>=Metodo!$C$43,"A",IF($L121>=Metodo!$C$44,"B","C"))) | N121: Nao contatado | Q121: Achar contato | T121: Tier 3 (varredura TomTom 2026-08-29, PR #185). Qualificacao: sem site.
A122: =IF($B122="","",ROW()-1) | L122: =IF($B122="","",IF($F122="",Metodo!$C$30,IF(AND($F122>=80,$F122<=250),Metodo!$C$28,IF(OR(AND($F122>=40,$F122<=79),AND($F122>=251,$F122<=400)),Metodo!$C$29,Metodo!$C$30)))+IFERROR(INDEX(Metodo!$C$32:$C$35,MATCH($G122,Metodo!$B$32:$B$35,0)),0)+COUNTIF($H122:$J122,"Sim")*Metodo!$C$37+IFERROR(INDEX(Metodo!$C$39:$C$41,MATCH($K122,Metodo!$B$39:$B$41,0)),0)) | M122: =IF($L122="","",IF($L122>=Metodo!$C$43,"A",IF($L122>=Metodo!$C$44,"B","C")))
A123: =IF($B123="","",ROW()-1) | L123: =IF($B123="","",IF($F123="",Metodo!$C$30,IF(AND($F123>=80,$F123<=250),Metodo!$C$28,IF(OR(AND($F123>=40,$F123<=79),AND($F123>=251,$F123<=400)),Metodo!$C$29,Metodo!$C$30)))+IFERROR(INDEX(Metodo!$C$32:$C$35,MATCH($G123,Metodo!$B$32:$B$35,0)),0)+COUNTIF($H123:$J123,"Sim")*Metodo!$C$37+IFERROR(INDEX(Metodo!$C$39:$C$41,MATCH($K123,Metodo!$B$39:$B$41,0)),0)) | M123: =IF($L123="","",IF($L123>=Metodo!$C$43,"A",IF($L123>=Metodo!$C$44,"B","C")))
A124: =IF($B124="","",ROW()-1) | L124: =IF($B124="","",IF($F124="",Metodo!$C$30,IF(AND($F124>=80,$F124<=250),Metodo!$C$28,IF(OR(AND($F124>=40,$F124<=79),AND($F124>=251,$F124<=400)),Metodo!$C$29,Metodo!$C$30)))+IFERROR(INDEX(Metodo!$C$32:$C$35,MATCH($G124,Metodo!$B$32:$B$35,0)),0)+COUNTIF($H124:$J124,"Sim")*Metodo!$C$37+IFERROR(INDEX(Metodo!$C$39:$C$41,MATCH($K124,Metodo!$B$39:$B$41,0)),0)) | M124: =IF($L124="","",IF($L124>=Metodo!$C$43,"A",IF($L124>=Metodo!$C$44,"B","C")))
A125: =IF($B125="","",ROW()-1) | L125: =IF($B125="","",IF($F125="",Metodo!$C$30,IF(AND($F125>=80,$F125<=250),Metodo!$C$28,IF(OR(AND($F125>=40,$F125<=79),AND($F125>=251,$F125<=400)),Metodo!$C$29,Metodo!$C$30)))+IFERROR(INDEX(Metodo!$C$32:$C$35,MATCH($G125,Metodo!$B$32:$B$35,0)),0)+COUNTIF($H125:$J125,"Sim")*Metodo!$C$37+IFERROR(INDEX(Metodo!$C$39:$C$41,MATCH($K125,Metodo!$B$39:$B$41,0)),0)) | M125: =IF($L125="","",IF($L125>=Metodo!$C$43,"A",IF($L125>=Metodo!$C$44,"B","C")))
A126: =IF($B126="","",ROW()-1) | L126: =IF($B126="","",IF($F126="",Metodo!$C$30,IF(AND($F126>=80,$F126<=250),Metodo!$C$28,IF(OR(AND($F126>=40,$F126<=79),AND($F126>=251,$F126<=400)),Metodo!$C$29,Metodo!$C$30)))+IFERROR(INDEX(Metodo!$C$32:$C$35,MATCH($G126,Metodo!$B$32:$B$35,0)),0)+COUNTIF($H126:$J126,"Sim")*Metodo!$C$37+IFERROR(INDEX(Metodo!$C$39:$C$41,MATCH($K126,Metodo!$B$39:$B$41,0)),0)) | M126: =IF($L126="","",IF($L126>=Metodo!$C$43,"A",IF($L126>=Metodo!$C$44,"B","C")))
A127: =IF($B127="","",ROW()-1) | L127: =IF($B127="","",IF($F127="",Metodo!$C$30,IF(AND($F127>=80,$F127<=250),Metodo!$C$28,IF(OR(AND($F127>=40,$F127<=79),AND($F127>=251,$F127<=400)),Metodo!$C$29,Metodo!$C$30)))+IFERROR(INDEX(Metodo!$C$32:$C$35,MATCH($G127,Metodo!$B$32:$B$35,0)),0)+COUNTIF($H127:$J127,"Sim")*Metodo!$C$37+IFERROR(INDEX(Metodo!$C$39:$C$41,MATCH($K127,Metodo!$B$39:$B$41,0)),0)) | M127: =IF($L127="","",IF($L127>=Metodo!$C$43,"A",IF($L127>=Metodo!$C$44,"B","C")))
...

Sheet Objecoes
B2: Log de objecoes
B3: Registre TODA objecao, inclusive a que voce respondeu bem. Este log e o rascunho do playbook da Fase 2 e, mais tarde, o insumo do Growth Engine.
B5: Data | C5: Box | D5: Objecao (palavras dele) | E5: Categoria | F5: Resposta que dei | G5: Funcionou? | H5: Virou venda? | J5: Ranking de objecoes
J6: Categoria | L6: Vezes
J7: Preco | L7: =COUNTIF($E$6:$E$105,"Preco")
J8: PIX / recorrencia | L8: =COUNTIF($E$6:$E$105,"PIX / recorrencia")
J9: Ja uso concorrente | L9: =COUNTIF($E$6:$E$105,"Ja uso concorrente")
J10: Agora nao / sem tempo | L10: =COUNTIF($E$6:$E$105,"Agora nao / sem tempo")
J11: Confianca (fundador solo) | L11: =COUNTIF($E$6:$E$105,"Confianca (fundador solo)")
J12: Falta feature | L12: =COUNTIF($E$6:$E$105,"Falta feature")
J13: Precisa falar com socio | L13: =COUNTIF($E$6:$E$105,"Precisa falar com socio")
J14: Outro | L14: =COUNTIF($E$6:$E$105,"Outro")
J16: A objecao do topo desta lista e a proxima prioridade de produto.
